Workbook

Sheet Read Me
B2: ALUMINIUM STORE
B3: Pricing Framework — v1.0
B4: A Specialised Operating Division of Besbpo Group · September 2026
B6: Overview
B7: This workbook prices all 2,147 SKUs in the Master Product Catalogue using a cost-basis engine: a Base Cost is built up from real physical inputs (aluminium weight, glass area, finish, hardware) on the Priced Catalogue sheet, then marked up per the Category Markup Bands and split into Retail / Trade / Volume tiers. Every price is a live formula — change an assumption on the Cost Assumptions or Markup Bands sheet and the full catalogue recalculates.
B9: How Base Cost is built
B10: Dimensioned finished products (windows, doors, skylights, garage doors, awnings, louvres, pergolas, carports, balcony/Juliet balustrades): Base Cost = opening area × a fully-loaded Area Rate for that product sub-category (frame, standard glazing/infill, and fabrication already included), plus a glazing upgrade differential where the line specifies IGU or another premium glazing over that product's baseline, plus a flat per-unit hardware allowance. The Area Rates are calibrated against real 2026 SA market pricing for equivalent products (see the Competitive Benchmark sheet) rather than built up from raw aluminium weight — an early first-principles version of this model, costed purely from profile weight and glass area, understated real finished-window and door pricing by roughly three times once checked against the market, because it missed the die, hardware, and fabrication value a finished system actually carries.
B11: Balustrade runs: Base Cost = length × (post/rail material cost, from aluminium weight/m and finish) + length × an infill rate that varies by type (glass, flat-bar, cable, or picket).
B12: Raw extrusion stock: priced on weight (length × profile kg/m × aluminium R/kg) plus finish — no fabrication loading and a thin resale margin, since this line sells to other fabricators as a near-commodity input rather than as a finished product.
B13: Non-dimensioned lines (shopfronts, curtain walling, partitioning, fascias/gutters, hardware, glass rate-card, sealants, fixings): Base Cost is a direct market-rate input (shown in blue), the same way the Area Rates and aluminium R/kg figures are inputs — these are still genuine costs, just not derived from a parsed dimension.
B15: Key assumptions (all illustrative — validate before going live)
B16: Aluminium cost: R18.5/kg — derived from an FOB South African mill-finish window/door profile quote of roughly US$1,050-1,200/tonne, converted at ~R16.40/USD. LME aluminium plus billet premium moves; re-check before relying on this for a live quote.
... B29: Priced Catalogue — all 2,147 SKUs with Base Cost, Markup %, and Retail/Trade/Volume price, live via formula.

Sheet Cost Assumptions
B1: COST ASSUMPTIONS
B2: Global Inputs
B3: Aluminium Cost (R/kg) | C3: 18.5
B4: Fabrication & Labour Loading (%) | C4: 0.32
B5: Flat-Bar / Panel Infill Rate (R/m²) | C5: 450
B7: Frame Weight per Linear Metre (kg/m) — extrusion stock & balustrade posts only
B8: WINDOW | C8: 1.7
B9: DOOR | C9: 2.3
B10: LIGHT | C10: 1.1
B11: STRUCTURAL | C11: 2.6
B12: BALUSTRADE | C12: 1.4
B15: Finish Cost per Linear Metre (R/m) — extrusion stock & balustrade posts only
B16: Natural Anodised | C16: 25
B17: Satin White (RAL 9016) | C17: 38
B18: Charcoal Grey (RAL 7016) | C18: 38
B19: Graphite Black (RAL 9005) | C19: 40
B20: Bronze Anodised | C20: 55
B23: Fully-Loaded Area Rate (R/m²) — windows, doors, pergolas/carports, screens, skylights, garage doors, balcony
B24: Sliding Windows | C24: 2300
B25: Casement Windows | C25: 2100
B26: Awning Windows | C26: 2150
B27: Hopper Windows | C27: 2000
B28: Louvre Windows | C28: 2400
B29: Fixed / Picture Windows | C29: 1750
B30: Tilt & Turn Windows | C30: 2800
B31: Bay & Bow Window Units | C31: 2600
B32: Sliding Doors | C32: 2050
B33: Stacking & Folding Doors | C33: 3200
B34: Hinged / Casement Doors | C34: 2300
B35: French Doors | C35: 2400
... B44: Balcony & Juliet Balustrades | C44: 1900
B47: Glazing Upgrade over Baseline (R/m²) — windows & doors only
B48: Standard Single-Glazed (4mm Clear Float) | C48: 0
B49: IGU Double-Glazed (4-12Ar-4 Low-E) | C49: 550
B50: 6.38mm Laminated Safety | C50: 0
B51: IGU Double-Glazed Laminated (6.38-12Ar-4 Low-E) | C51: 700
B52: 4mm Clear Float | C52: 0
B53: 6mm Toughened Louvre Blade | C53: 0
B54: Aluminium Louvre Blade | C54: 0
B55: Stainless Security Mesh | C55: 0
B56: 10mm Toughened Glass | C56: 350
B59: Glass / Glazing Rate (R/m²) — shopfront, curtain walling, partitioning, raw glass card
B60: 4mm Clear Float | C60: 190
B61: 6mm Toughened Louvre Blade | C61: 320
B62: Standard Single-Glazed (4mm Clear Float) | C62: 190
B63: IGU Double-Glazed (4-12Ar-4 Low-E) | C63: 950
B64: 6.38mm Laminated Safety | C64: 420
B65: IGU Double-Glazed Laminated (6.38-12Ar-4 Low-E) | C65: 1250
B66: Solar-Control Tinted IGU | C66: 1100
B67: Aluminium Louvre Blade | C67: 0
B68: Stainless Security Mesh | C68: 0
B69: 10mm Toughened Glass | C69: 560
B70: Float Glass — Clear 4mm | C70: 190
B71: Float Glass — Clear 5mm | C71: 230
... B90: Mirror Glass 6mm | C90: 400
B93: Hardware Allowance per Unit (R/each)
B94: Windows | C94: 250
B95: Doors | C95: 550
B96: Security & Screen Doors | C96: 300
B97: Skylights & Roof Glazing | C97: 180
B98: Garage Doors | C98: 950
B99: Awnings & Canopy Shading | C99: 350
B100: Louvres & Privacy Screens | C100: 150
B101: Balcony & Juliet Balustrades | C101: 200
B102: Pergolas | C102: 420
B103: Carports & Canopies | C103: 500
B106: Balustrade Infill Rate (R per metre run)
B107: Glass-Infill Balustrade (Post & Handrail) | C107: 2200
B108: Flat-Bar Infill Balustrade | C108: 1400
B109: Cable-Infill Balustrade | C109: 1800
B110: Picket-Infill Balustrade | C110: 1200
B113: Extrusion Shape Weight per Metre (kg/m)
B114: Box Section 20x20mm | C114: 0.22
B115: Box Section 25x25mm | C115: 0.28
B116: Box Section 40x40mm | C116: 0.52
B117: Box Section 50x50mm | C117: 0.68
B118: Angle 25x25x3mm | C118: 0.19
B119: Angle 40x40x3mm | C119: 0.31
B120: Flat Bar 25x3mm | C120: 0.2
B121: Flat Bar 40x5mm | C121: 0.54
B122: Round Tube 25mm OD | C122: 0.24
B123: Round Tube 32mm OD | C123: 0.32
B124: U-Channel 20x20x2mm | C124: 0.21
B125: T-Section 25x25x3mm | C125: 0.23

Sheet Category Markup Bands
A1: Category | B1: Sub-Category (override, if any) | C1: Markup %
A2: Windows | B2: — (applies to all sub-categories) | C2: 0.42
A3: Doors | B3: — (applies to all sub-categories) | C3: 0.4
A4: Facade & Structural Systems | B4: — (applies to all sub-categories) | C4: 0.3
A5: Outdoor Living & Shading | B5: — (applies to all sub-categories) | C5: 0.45
A6: Railing & Screening Systems | B6: — (applies to all sub-categories) | C6: 0.42
A7: Roofing Glazing & Garage Doors | B7: — (applies to all sub-categories) | C7: 0.38
A8: Raw Material & Hardware
A9: Raw Material & Hardware | B9: Extrusion Profiles & Raw Stock | C9: 0.18
A10: Raw Material & Hardware | B10: Hardware & Ironmongery | C10: 0.48
A11: Raw Material & Hardware | B11: Glazing & Glass | C11: 0.25
A12: Raw Material & Hardware | B12: Sealants, Gaskets & Weatherproofing | C12: 0.55
A13: Raw Material & Hardware | B13: Fixings, Fasteners & Brackets | C13: 0.55

Sheet Customer Tiers
A1: Tier | B1: Discount off Retail
A2: Retail (List Price) | B2: 0
A3: Trade | B3: 0.12
A4: Volume | B4: 0.2
A6: Trade tier: registered installers, builders, and fabricators buying on account.
A7: Volume tier: developer/contractor project quantities and CMI Partner Network project work.

Sheet Delivery & Additional Charges
A1: Charge | B1: Rate
A2: Local delivery — within 30km of nearest yard/branch (standard goods, up to 1,000kg) | B2: 850
A3: Local delivery — within 30km, 1,000–3,000kg | B3: 1150
A4: Local delivery — above 3,000kg or beyond 30km | B4: Quote individually
A5: Fragile-goods handling surcharge — glazed units, curtain-wall/shopfront panels (% of order value) | B5: 0.08
A6: Oversized/abnormal load permit — case-by-case (long extrusion runs, large structural members) | B6: Quote individually
A7: Made-to-Order lead time — standard finish, standard glazing | B7: Quote individually
A8: Made-to-Order lead time — CMI Partner Network (curtain walling, large facade packages) | B8: Quote individually
A10: Delivery banding follows the same weight-based, distance-banded model standing as policy on Roofsteel; the fragile-goods surcharge is new for glazed product.

Sheet Competitive Benchmark
A1: Product Line | B1: SA Market Range (2026) | C1: Aluminium Store Retail (comparable size) | D1: Source / Note
A2: Standard sliding window (1209×909mm) | B2: R2,500 – R6,000 | C2: ='Priced Catalogue'!R22 -> 3944.2719 | D2: Van Acht (Gauteng/North West/Western Cape installer), 2026 published guide pricing
A3: Casement window (1209×1209mm) | B3: R3,000 – R7,000 | C3: ='Priced Catalogue'!R272 -> 4713.7327 | D3: Van Acht, 2026 published guide pricing
A4: Custom/large window (2409×1509mm fixed) | B4: R8,000 – R20,000+ | C4: ='Priced Catalogue'!R646 -> 9388.4248 | D4: Van Acht, 2026 published guide pricing
A5: Standard sliding door (1809×2090mm) | B5: R8,000 – R15,000 | C5: ='Priced Catalogue'!R784 -> 11620.925 | D5: Van Acht, 2026 published guide pricing
A6: Stacking/folding door (3-leaf, 3609×2090mm) | B6: R25,000 – R60,000+ | C6: ='Priced Catalogue'!R1024 -> 34561.789 | D6: Van Acht, 2026 published guide pricing
A7: Standard framed pivot door (1509×2700mm) — see note | B7: R40,000 – R100,000+ (frameless, not this line) | C7: ='Priced Catalogue'!R1310 -> 20734.07 | D7: Van Acht cites this range for fully frameless structural-glass entrance systems — a different product to the standard framed Pivot Door priced alongside it here. A directly comparable frameless system would be quoted through Curtain Walling / Structural Glazing (per m²), not this catalogue line.
A9: Comparable-size cell references point at specific rows in the Priced Catalogue; re-check the row references if the catalogue is re-sorted or re-filtered.

Sheet Priced Catalogue
A1: SKU | B1: Category | C1: Sub-Category | D1: Product Name | E1: Configuration | F1: Standard Size | G1: Finish | H1: Glazing / Material Spec | I1: Unit of Sale | J1: Segment(s) Served | K1: Fulfilment Type | L1: Frame Class | M1: Width (mm) | N1: Height (mm) | O1: Length (m) | P1: Base Cost (R) | Q1: Markup % | R1: Retail (R) | S1: Trade (R) | T1: Volume (R)
A2: ALS-SLW-0001 | B2: Windows | C2: Sliding Windows | D2: Aluminium Sliding Window — 2-Pane Slider (1 Fixed + 1 Sliding) — 609x609mm — Natural Anodised — Standard Single-Glazed (4mm Clear Float) | E2: 2-Pane Slider (1 Fixed + 1 Sliding) | F2: 609x609mm | G2: Natural Anodised | H2: Standard Single-Glazed (4mm Clear Float) | I2: Each | J2: Residential/Commercial | K2: Stock | L2: WINDOW | M2: 609 | N2: 609 | P2: =(M2*N2/1000000)*(INDEX(AreaRate_Vals,MATCH(C2,AreaRate_Keys,0))+IFERROR(INDEX(GlazingUpg_Vals,MATCH(H2,GlazingUpg_Keys,0)),0))+INDEX(Hardware_Vals,MATCH("Windows",Hardware_Keys,0)) -> 1103.0263 | Q2: =INDEX(Markup_Vals,MATCH("Windows",MarkupCat_Keys,0)) -> 0.42 | R2: =P2*(1+Q2) -> 1566.2973 | S2: =R2*(1-TradeDiscount) -> 1378.3417 | T2: =R2*(1-VolumeDiscount) -> 1253.0379
A3: ALS-SLW-0002 | B3: Windows | C3: Sliding Windows | D3: Aluminium Sliding Window — 2-Pane Slider (1 Fixed + 1 Sliding) — 609x609mm — Satin White (RAL 9016) — Standard Single-Glazed (4mm Clear Float) | E3: 2-Pane Slider (1 Fixed + 1 Sliding) | F3: 609x609mm | G3: Satin White (RAL 9016) | H3: Standard Single-Glazed (4mm Clear Float) | I3: Each | J3: Residential/Commercial | K3: Stock | L3: WINDOW | M3: 609 | N3: 609 | P3: =(M3*N3/1000000)*(INDEX(AreaRate_Vals,MATCH(C3,AreaRate_Keys,0))+IFERROR(INDEX(GlazingUpg_Vals,MATCH(H3,GlazingUpg_Keys,0)),0))+INDEX(Hardware_Vals,MATCH("Windows",Hardware_Keys,0)) -> 1103.0263 | Q3: =INDEX(Markup_Vals,MATCH("Windows",MarkupCat_Keys,0)) -> 0.42 | R3: =P3*(1+Q3) -> 1566.2973 | S3: =R3*(1-TradeDiscount) -> 1378.3417 | T3: =R3*(1-VolumeDiscount) -> 1253.0379
A4: ALS-SLW-0003 | B4: Windows | C4: Sliding Windows | D4: Aluminium Sliding Window — 2-Pane Slider (1 Fixed + 1 Sliding) — 609x609mm — Charcoal Grey (RAL 7016) — Standard Single-Glazed (4mm Clear Float) | E4: 2-Pane Slider (1 Fixed + 1 Sliding) | F4: 609x609mm | G4: Charcoal Grey (RAL 7016) | H4: Standard Single-Glazed (4mm Clear Float) | I4: Each | J4: Residential/Commercial | K4: Stock | L4: WINDOW | M4: 609 | N4: 609 | P4: =(M4*N4/1000000)*(INDEX(AreaRate_Vals,MATCH(C4,AreaRate_Keys,0))+IFERROR(INDEX(GlazingUpg_Vals,MATCH(H4,GlazingUpg_Keys,0)),0))+INDEX(Hardware_Vals,MATCH("Windows",Hardware_Keys,0)) -> 1103.0263 | Q4: =INDEX(Markup_Vals,MATCH("Windows",MarkupCat_Keys,0)) -> 0.42 | R4: =P4*(1+Q4) -> 1566.2973 | S4: =R4*(1-TradeDiscount) -> 1378.3417 | T4: =R4*(1-VolumeDiscount) -> 1253.0379
A5: ALS-SLW-0004 | B5: Windows | C5: Sliding Windows | D5: Aluminium Sliding Window — 2-Pane Slider (1 Fixed + 1 Sliding) — 609x609mm — Bronze Anodised — Standard Single-Glazed (4mm Clear Float) | E5: 2-Pane Slider (1 Fixed + 1 Sliding) | F5: 609x609mm | G5: Bronze Anodised | H5: Standard Single-Glazed (4mm Clear Float) | I5: Each | J5: Residential/Commercial | K5: Stock | L5: WINDOW | M5: 609 | N5: 609 | P5: =(M5*N5/1000000)*(INDEX(AreaRate_Vals,MATCH(C5,AreaRate_Keys,0))+IFERROR(INDEX(GlazingUpg_Vals,MATCH(H5,GlazingUpg_Keys,0)),0))+INDEX(Hardware_Vals,MATCH("Windows",Hardware_Keys,0)) -> 1103.0263 | Q5: =INDEX(Markup_Vals,MATCH("Windows",MarkupCat_Keys,0)) -> 0.42 | R5: =P5*(1+Q5) -> 1566.2973 | S5: =R5*(1-TradeDiscount) -> 1378.3417 | T5: =R5*(1-VolumeDiscount) -> 1253.0379
A6: ALS-SLW-0005 | B6: Windows | C6: Sliding Windows | D6: Aluminium Sliding Window — 2-Pane Slider (1 Fixed + 1 Sliding) — 609x609mm — Graphite Black (RAL 9005) — Standard Single-Glazed (4mm Clear Float) | E6: 2-Pane Slider (1 Fixed + 1 Sliding) | F6: 609x609mm | G6: Graphite Black (RAL 9005) | H6: Standard Single-Glazed (4mm Clear Float) | I6: Each | J6: Residential/Commercial | K6: Stock | L6: WINDOW | M6: 609 | N6: 609 | P6: =(M6*N6/1000000)*(INDEX(AreaRate_Vals,MATCH(C6,AreaRate_Keys,0))+IFERROR(INDEX(GlazingUpg_Vals,MATCH(H6,GlazingUpg_Keys,0)),0))+INDEX(Hardware_Vals,MATCH("Windows",Hardware_Keys,0)) -> 1103.0263 | Q6: =INDEX(Markup_Vals,MATCH("Windows",MarkupCat_Keys,0)) -> 0.42 | R6: =P6*(1+Q6) -> 1566.2973 | S6: =R6*(1-TradeDiscount) -> 1378.3417 | T6: =R6*(1-VolumeDiscount) -> 1253.0379
A7: ALS-SLW-0006 | B7: Windows | C7: Sliding Windows | D7: Aluminium Sliding Window — 2-Pane Slider (1 Fixed + 1 Sliding) — 609x609mm — Natural Anodised — IGU Double-Glazed (4-12Ar-4 Low-E) | E7: 2-Pane Slider (1 Fixed + 1 Sliding) | F7: 609x609mm | G7: Natural Anodised | H7: IGU Double-Glazed (4-12Ar-4 Low-E) | I7: Each | J7: Residential/Commercial | K7: Stock | L7: WINDOW | M7: 609 | N7: 609 | P7: =(M7*N7/1000000)*(INDEX(AreaRate_Vals,MATCH(C7,AreaRate_Keys,0))+IFERROR(INDEX(GlazingUpg_Vals,MATCH(H7,GlazingUpg_Keys,0)),0))+INDEX(Hardware_Vals,MATCH("Windows",Hardware_Keys,0)) -> 1307.0108 | Q7: =INDEX(Markup_Vals,MATCH("Windows",MarkupCat_Keys,0)) -> 0.42 | R7: =P7*(1+Q7) -> 1855.9554 | S7: =R7*(1-TradeDiscount) -> 1633.2408 | T7: =R7*(1-VolumeDiscount) -> 1484.7643
A8: ALS-SLW-0007 | B8: Windows | C8: Sliding Windows | D8: Aluminium Sliding Window — 2-Pane Slider (1 Fixed + 1 Sliding) — 609x609mm — Satin White (RAL 9016) — IGU Double-Glazed (4-12Ar-4 Low-E) | E8: 2-Pane Slider (1 Fixed + 1 Sliding) | F8: 609x609mm | G8: Satin White (RAL 9016) | H8: IGU Double-Glazed (4-12Ar-4 Low-E) | I8: Each | J8: Residential/Commercial | K8: Stock | L8: WINDOW | M8: 609 | N8: 609 | P8: =(M8*N8/1000000)*(INDEX(AreaRate_Vals,MATCH(C8,AreaRate_Keys,0))+IFERROR(INDEX(GlazingUpg_Vals,MATCH(H8,GlazingUpg_Keys,0)),0))+INDEX(Hardware_Vals,MATCH("Windows",Hardware_Keys,0)) -> 1307.0108 | Q8: =INDEX(Markup_Vals,MATCH("Windows",MarkupCat_Keys,0)) -> 0.42 | R8: =P8*(1+Q8) -> 1855.9554 | S8: =R8*(1-TradeDiscount) -> 1633.2408 | T8: =R8*(1-VolumeDiscount) -> 1484.7643
A9: ALS-SLW-0008 | B9: Windows | C9: Sliding Windows | D9: Aluminium Sliding Window — 2-Pane Slider (1 Fixed + 1 Sliding) — 609x609mm — Charcoal Grey (RAL 7016) — IGU Double-Glazed (4-12Ar-4 Low-E) | E9: 2-Pane Slider (1 Fixed + 1 Sliding) | F9: 609x609mm | G9: Charcoal Grey (RAL 7016) | H9: IGU Double-Glazed (4-12Ar-4 Low-E) | I9: Each | J9: Residential/Commercial | K9: Stock | L9: WINDOW | M9: 609 | N9: 609 | P9: =(M9*N9/1000000)*(INDEX(AreaRate_Vals,MATCH(C9,AreaRate_Keys,0))+IFERROR(INDEX(GlazingUpg_Vals,MATCH(H9,GlazingUpg_Keys,0)),0))+INDEX(Hardware_Vals,MATCH("Windows",Hardware_Keys,0)) -> 1307.0108 | Q9: =INDEX(Markup_Vals,MATCH("Windows",MarkupCat_Keys,0)) -> 0.42 | R9: =P9*(1+Q9) -> 1855.9554 | S9: =R9*(1-TradeDiscount) -> 1633.2408 | T9: =R9*(1-VolumeDiscount) -> 1484.7643
A10: ALS-SLW-0009 | B10: Windows | C10: Sliding Windows | D10: Aluminium Sliding Window — 2-Pane Slider (1 Fixed + 1 Sliding) — 609x609mm — Bronze Anodised — IGU Double-Glazed (4-12Ar-4 Low-E) | E10: 2-Pane Slider (1 Fixed + 1 Sliding) | F10: 609x609mm | G10: Bronze Anodised | H10: IGU Double-Glazed (4-12Ar-4 Low-E) | I10: Each | J10: Residential/Commercial | K10: Stock | L10: WINDOW | M10: 609 | N10: 609 | P10: =(M10*N10/1000000)*(INDEX(AreaRate_Vals,MATCH(C10,AreaRate_Keys,0))+IFERROR(INDEX(GlazingUpg_Vals,MATCH(H10,GlazingUpg_Keys,0)),0))+INDEX(Hardware_Vals,MATCH("Windows",Hardware_Keys,0)) -> 1307.0108 | Q10: =INDEX(Markup_Vals,MATCH("Windows",MarkupCat_Keys,0)) -> 0.42 | R10: =P10*(1+Q10) -> 1855.9554 | S10: =R10*(1-TradeDiscount) -> 1633.2408 | T10: =R10*(1-VolumeDiscount) -> 1484.7643
A11: ALS-SLW-0010 | B11: Windows | C11: Sliding Windows | D11: Aluminium Sliding Window — 2-Pane Slider (1 Fixed + 1 Sliding) — 609x609mm — Graphite Black (RAL 9005) — IGU Double-Glazed (4-12Ar-4 Low-E) | E11: 2-Pane Slider (1 Fixed + 1 Sliding) | F11: 609x609mm | G11: Graphite Black (RAL 9005) | H11: IGU Double-Glazed (4-12Ar-4 Low-E) | I11: Each | J11: Residential/Commercial | K11: Stock | L11: WINDOW | M11: 609 | N11: 609 | P11: =(M11*N11/1000000)*(INDEX(AreaRate_Vals,MATCH(C11,AreaRate_Keys,0))+IFERROR(INDEX(GlazingUpg_Vals,MATCH(H11,GlazingUpg_Keys,0)),0))+INDEX(Hardware_Vals,MATCH("Windows",Hardware_Keys,0)) -> 1307.0108 | Q11: =INDEX(Markup_Vals,MATCH("Windows",MarkupCat_Keys,0)) -> 0.42 | R11: =P11*(1+Q11) -> 1855.9554 | S11: =R11*(1-TradeDiscount) -> 1633.2408 | T11: =R11*(1-VolumeDiscount) -> 1484.7643
A12: ALS-SLW-0011 | B12: Windows | C12: Sliding Windows | D12: Aluminium Sliding Window — 2-Pane Slider (1 Fixed + 1 Sliding) — 1209x609mm — Natural Anodised — Standard Single-Glazed (4mm Clear Float) | E12: 2-Pane Slider (1 Fixed + 1 Sliding) | F12: 1209x609mm | G12: Natural Anodised | H12: Standard Single-Glazed (4mm Clear Float) | I12: Each | J12: Residential/Commercial | K12: Stock | L12: WINDOW | M12: 1209 | N12: 609 | P12: =(M12*N12/1000000)*(INDEX(AreaRate_Vals,MATCH(C12,AreaRate_Keys,0))+IFERROR(INDEX(GlazingUpg_Vals,MATCH(H12,GlazingUpg_Keys,0)),0))+INDEX(Hardware_Vals,MATCH("Windows",Hardware_Keys,0)) -> 1943.4463 | Q12: =INDEX(Markup_Vals,MATCH("Windows",MarkupCat_Keys,0)) -> 0.42 | R12: =P12*(1+Q12) -> 2759.6937 | S12: =R12*(1-TradeDiscount) -> 2428.5305 | T12: =R12*(1-VolumeDiscount) -> 2207.755
A13: ALS-SLW-0012 | B13: Windows | C13: Sliding Windows | D13: Aluminium Sliding Window — 2-Pane Slider (1 Fixed + 1 Sliding) — 1209x609mm — Satin White (RAL 9016) — Standard Single-Glazed (4mm Clear Float) | E13: 2-Pane Slider (1 Fixed + 1 Sliding) | F13: 1209x609mm | G13: Satin White (RAL 9016) | H13: Standard Single-Glazed (4mm Clear Float) | I13: Each | J13: Residential/Commercial | K13: Stock | L13: WINDOW | M13: 1209 | N13: 609 | P13: =(M13*N13/1000000)*(INDEX(AreaRate_Vals,MATCH(C13,AreaRate_Keys,0))+IFERROR(INDEX(GlazingUpg_Vals,MATCH(H13,GlazingUpg_Keys,0)),0))+INDEX(Hardware_Vals,MATCH("Windows",Hardware_Keys,0)) -> 1943.4463 | Q13: =INDEX(Markup_Vals,MATCH("Windows",MarkupCat_Keys,0)) -> 0.42 | R13: =P13*(1+Q13) -> 2759.6937 | S13: =R13*(1-TradeDiscount) -> 2428.5305 | T13: =R13*(1-VolumeDiscount) -> 2207.755
... A763: ALS-BBW-0048 | B763: Windows | C763: Bay & Bow Window Units | D763: Aluminium Box Bay (90° Square) Window Unit — 3009x1809mm — Bronze Anodised | E763: Box Bay (90° Square) | F763: 3009x1809mm | G763: Bronze Anodised | H763: 4mm Clear Float | I763: Each | J763: Residential | K763: Made-to-Order | L763: WINDOW | M763: 3009 | N763: 1809 | P763: =(M763*N763/1000000)*(INDEX(AreaRate_Vals,MATCH(C763,AreaRate_Keys,0))+IFERROR(INDEX(GlazingUpg_Vals,MATCH(H763,GlazingUpg_Keys,0)),0))+INDEX(Hardware_Vals,MATCH("Windows",Hardware_Keys,0)) -> 14402.531 | Q763: =INDEX(Markup_Vals,MATCH("Windows",MarkupCat_Keys,0)) -> 0.42 | R763: =P763*(1+Q763) -> 20451.593 | S763: =R763*(1-TradeDiscount) -> 17997.402 | T763: =R763*(1-VolumeDiscount) -> 16361.275
A764: ALS-SLD-0001 | B764: Doors | C764: Sliding Doors | D764: Aluminium Sliding Door — 2-Panel Slider (1 Fixed + 1 Sliding) — 1809x2009mm — Natural Anodised — 6.38mm Laminated Safety | E764: 2-Panel Slider (1 Fixed + 1 Sliding) | F764: 1809x2009mm | G764: Natural Anodised | H764: 6.38mm Laminated Safety | I764: Each | J764: Residential/Commercial | K764: Stock | L764: DOOR | M764: 1809 | N764: 2009 | P764: =(M764*N764/1000000)*(INDEX(AreaRate_Vals,MATCH(C764,AreaRate_Keys,0))+IFERROR(INDEX(GlazingUpg_Vals,MATCH(H764,GlazingUpg_Keys,0)),0))+INDEX(Hardware_Vals,MATCH("Doors",Hardware_Keys,0)) -> 8000.2761 | Q764: =INDEX(Markup_Vals,MATCH("Doors",MarkupCat_Keys,0)) -> 0.4 | R764: =P764*(1+Q764) -> 11200.386 | S764: =R764*(1-TradeDiscount) -> 9856.3401 | T764: =R764*(1-VolumeDiscount) -> 8960.3092
A765: ALS-SLD-0002 | B765: Doors | C765: Sliding Doors | D765: Aluminium Sliding Door — 2-Panel Slider (1 Fixed + 1 Sliding) — 1809x2009mm — Satin White (RAL 9016) — 6.38mm Laminated Safety | E765: 2-Panel Slider (1 Fixed + 1 Sliding) | F765: 1809x2009mm | G765: Satin White (RAL 9016) | H765: 6.38mm Laminated Safety | I765: Each | J765: Residential/Commercial | K765: Stock | L765: DOOR | M765: 1809 | N765: 2009 | P765: =(M765*N765/1000000)*(INDEX(AreaRate_Vals,MATCH(C765,AreaRate_Keys,0))+IFERROR(INDEX(GlazingUpg_Vals,MATCH(H765,GlazingUpg_Keys,0)),0))+INDEX(Hardware_Vals,MATCH("Doors",Hardware_Keys,0)) -> 8000.2761 | Q765: =INDEX(Markup_Vals,MATCH("Doors",MarkupCat_Keys,0)) -> 0.4 | R765: =P765*(1+Q765) -> 11200.386 | S765: =R765*(1-TradeDiscount) -> 9856.3401 | T765: =R765*(1-VolumeDiscount) -> 8960.3092
A766: ALS-SLD-0003 | B766: Doors | C766: Sliding Doors | D766: Aluminium Sliding Door — 2-Panel Slider (1 Fixed + 1 Sliding) — 1809x2009mm — Charcoal Grey (RAL 7016) — 6.38mm Laminated Safety | E766: 2-Panel Slider (1 Fixed + 1 Sliding) | F766: 1809x2009mm | G766: Charcoal Grey (RAL 7016) | H766: 6.38mm Laminated Safety | I766: Each | J766: Residential/Commercial | K766: Stock | L766: DOOR | M766: 1809 | N766: 2009 | P766: =(M766*N766/1000000)*(INDEX(AreaRate_Vals,MATCH(C766,AreaRate_Keys,0))+IFERROR(INDEX(GlazingUpg_Vals,MATCH(H766,GlazingUpg_Keys,0)),0))+INDEX(Hardware_Vals,MATCH("Doors",Hardware_Keys,0)) -> 8000.2761 | Q766: =INDEX(Markup_Vals,MATCH("Doors",MarkupCat_Keys,0)) -> 0.4 | R766: =P766*(1+Q766) -> 11200.386 | S766: =R766*(1-TradeDiscount) -> 9856.3401 | T766: =R766*(1-VolumeDiscount) -> 8960.3092
A767: ALS-SLD-0004 | B767: Doors | C767: Sliding Doors | D767: Aluminium Sliding Door — 2-Panel Slider (1 Fixed + 1 Sliding) — 1809x2009mm — Bronze Anodised — 6.38mm Laminated Safety | E767: 2-Panel Slider (1 Fixed + 1 Sliding) | F767: 1809x2009mm | G767: Bronze Anodised | H767: 6.38mm Laminated Safety | I767: Each | J767: Residential/Commercial | K767: Stock | L767: DOOR | M767: 1809 | N767: 2009 | P767: =(M767*N767/1000000)*(INDEX(AreaRate_Vals,MATCH(C767,AreaRate_Keys,0))+IFERROR(INDEX(GlazingUpg_Vals,MATCH(H767,GlazingUpg_Keys,0)),0))+INDEX(Hardware_Vals,MATCH("Doors",Hardware_Keys,0)) -> 8000.2761 | Q767: =INDEX(Markup_Vals,MATCH("Doors",MarkupCat_Keys,0)) -> 0.4 | R767: =P767*(1+Q767) -> 11200.386 | S767: =R767*(1-TradeDiscount) -> 9856.3401 | T767: =R767*(1-VolumeDiscount) -> 8960.3092
A768: ALS-SLD-0005 | B768: Doors | C768: Sliding Doors | D768: Aluminium Sliding Door — 2-Panel Slider (1 Fixed + 1 Sliding) — 1809x2009mm — Graphite Black (RAL 9005) — 6.38mm Laminated Safety | E768: 2-Panel Slider (1 Fixed + 1 Sliding) | F768: 1809x2009mm | G768: Graphite Black (RAL 9005) | H768: 6.38mm Laminated Safety | I768: Each | J768: Residential/Commercial | K768: Stock | L768: DOOR | M768: 1809 | N768: 2009 | P768: =(M768*N768/1000000)*(INDEX(AreaRate_Vals,MATCH(C768,AreaRate_Keys,0))+IFERROR(INDEX(GlazingUpg_Vals,MATCH(H768,GlazingUpg_Keys,0)),0))+INDEX(Hardware_Vals,MATCH("Doors",Hardware_Keys,0)) -> 8000.2761 | Q768: =INDEX(Markup_Vals,MATCH("Doors",MarkupCat_Keys,0)) -> 0.4 | R768: =P768*(1+Q768) -> 11200.386 | S768: =R768*(1-TradeDiscount) -> 9856.3401 | T768: =R768*(1-VolumeDiscount) -> 8960.3092
A769: ALS-SLD-0006 | B769: Doors | C769: Sliding Doors | D769: Aluminium Sliding Door — 2-Panel Slider (1 Fixed + 1 Sliding) — 1809x2009mm — Natural Anodised — IGU Double-Glazed Laminated (6.38-12Ar-4 Low-E) | E769: 2-Panel Slider (1 Fixed + 1 Sliding) | F769: 1809x2009mm | G769: Natural Anodised | H769: IGU Double-Glazed Laminated (6.38-12Ar-4 Low-E) | I769: Each | J769: Residential/Commercial | K769: Stock | L769: DOOR | M769: 1809 | N769: 2009 | P769: =(M769*N769/1000000)*(INDEX(AreaRate_Vals,MATCH(C769,AreaRate_Keys,0))+IFERROR(INDEX(GlazingUpg_Vals,MATCH(H769,GlazingUpg_Keys,0)),0))+INDEX(Hardware_Vals,MATCH("Doors",Hardware_Keys,0)) -> 10544.273 | Q769: =INDEX(Markup_Vals,MATCH("Doors",MarkupCat_Keys,0)) -> 0.4 | R769: =P769*(1+Q769) -> 14761.982 | S769: =R769*(1-TradeDiscount) -> 12990.544 | T769: =R769*(1-VolumeDiscount) -> 11809.585
A770: ALS-SLD-0007 | B770: Doors | C770: Sliding Doors | D770: Aluminium Sliding Door — 2-Panel Slider (1 Fixed + 1 Sliding) — 1809x2009mm — Satin White (RAL 9016) — IGU Double-Glazed Laminated (6.38-12Ar-4 Low-E) | E770: 2-Panel Slider (1 Fixed + 1 Sliding) | F770: 1809x2009mm | G770: Satin White (RAL 9016) | H770: IGU Double-Glazed Laminated (6.38-12Ar-4 Low-E) | I770: Each | J770: Residential/Commercial | K770: Stock | L770: DOOR | M770: 1809 | N770: 2009 | P770: =(M770*N770/1000000)*(INDEX(AreaRate_Vals,MATCH(C770,AreaRate_Keys,0))+IFERROR(INDEX(GlazingUpg_Vals,MATCH(H770,GlazingUpg_Keys,0)),0))+INDEX(Hardware_Vals,MATCH("Doors",Hardware_Keys,0)) -> 10544.273 | Q770: =INDEX(Markup_Vals,MATCH("Doors",MarkupCat_Keys,0)) -> 0.4 | R770: =P770*(1+Q770) -> 14761.982 | S770: =R770*(1-TradeDiscount) -> 12990.544 | T770: =R770*(1-VolumeDiscount) -> 11809.585
A771: ALS-SLD-0008 | B771: Doors | C771: Sliding Doors | D771: Aluminium Sliding Door — 2-Panel Slider (1 Fixed + 1 Sliding) — 1809x2009mm — Charcoal Grey (RAL 7016) — IGU Double-Glazed Laminated (6.38-12Ar-4 Low-E) | E771: 2-Panel Slider (1 Fixed + 1 Sliding) | F771: 1809x2009mm | G771: Charcoal Grey (RAL 7016) | H771: IGU Double-Glazed Laminated (6.38-12Ar-4 Low-E) | I771: Each | J771: Residential/Commercial | K771: Stock | L771: DOOR | M771: 1809 | N771: 2009 | P771: =(M771*N771/1000000)*(INDEX(AreaRate_Vals,MATCH(C771,AreaRate_Keys,0))+IFERROR(INDEX(GlazingUpg_Vals,MATCH(H771,GlazingUpg_Keys,0)),0))+INDEX(Hardware_Vals,MATCH("Doors",Hardware_Keys,0)) -> 10544.273 | Q771: =INDEX(Markup_Vals,MATCH("Doors",MarkupCat_Keys,0)) -> 0.4 | R771: =P771*(1+Q771) -> 14761.982 | S771: =R771*(1-TradeDiscount) -> 12990.544 | T771: =R771*(1-VolumeDiscount) -> 11809.585
A772: ALS-SLD-0009 | B772: Doors | C772: Sliding Doors | D772: Aluminium Sliding Door — 2-Panel Slider (1 Fixed + 1 Sliding) — 1809x2009mm — Bronze Anodised — IGU Double-Glazed Laminated (6.38-12Ar-4 Low-E) | E772: 2-Panel Slider (1 Fixed + 1 Sliding) | F772: 1809x2009mm | G772: Bronze Anodised | H772: IGU Double-Glazed Laminated (6.38-12Ar-4 Low-E) | I772: Each | J772: Residential/Commercial | K772: Stock | L772: DOOR | M772: 1809 | N772: 2009 | P772: =(M772*N772/1000000)*(INDEX(AreaRate_Vals,MATCH(C772,AreaRate_Keys,0))+IFERROR(INDEX(GlazingUpg_Vals,MATCH(H772,GlazingUpg_Keys,0)),0))+INDEX(Hardware_Vals,MATCH("Doors",Hardware_Keys,0)) -> 10544.273 | Q772: =INDEX(Markup_Vals,MATCH("Doors",MarkupCat_Keys,0)) -> 0.4 | R772: =P772*(1+Q772) -> 14761.982 | S772: =R772*(1-TradeDiscount) -> 12990.544 | T772: =R772*(1-VolumeDiscount) -> 11809.585
A773: ALS-SLD-0010 | B773: Doors | C773: Sliding Doors | D773: Aluminium Sliding Door — 2-Panel Slider (1 Fixed + 1 Sliding) — 1809x2009mm — Graphite Black (RAL 9005) — IGU Double-Glazed Laminated (6.38-12Ar-4 Low-E) | E773: 2-Panel Slider (1 Fixed + 1 Sliding) | F773: 1809x2009mm | G773: Graphite Black (RAL 9005) | H773: IGU Double-Glazed Laminated (6.38-12Ar-4 Low-E) | I773: Each | J773: Residential/Commercial | K773: Stock | L773: DOOR | M773: 1809 | N773: 2009 | P773: =(M773*N773/1000000)*(INDEX(AreaRate_Vals,MATCH(C773,AreaRate_Keys,0))+IFERROR(INDEX(GlazingUpg_Vals,MATCH(H773,GlazingUpg_Keys,0)),0))+INDEX(Hardware_Vals,MATCH("Doors",Hardware_Keys,0)) -> 10544.273 | Q773: =INDEX(Markup_Vals,MATCH("Doors",MarkupCat_Keys,0)) -> 0.4 | R773: =P773*(1+Q773) -> 14761.982 | S773: =R773*(1-TradeDiscount) -> 12990.544 | T773: =R773*(1-VolumeDiscount) -> 11809.585
A774: ALS-SLD-0011 | B774: Doors | C774: Sliding Doors | D774: Aluminium Sliding Door — 2-Panel Slider (1 Fixed + 1 Sliding) — 2409x2009mm — Natural Anodised — 6.38mm Laminated Safety | E774: 2-Panel Slider (1 Fixed + 1 Sliding) | F774: 2409x2009mm | G774: Natural Anodised | H774: 6.38mm Laminated Safety | I774: Each | J774: Residential/Commercial | K774: Stock | L774: DOOR | M774: 2409 | N774: 2009 | P774: =(M774*N774/1000000)*(INDEX(AreaRate_Vals,MATCH(C774,AreaRate_Keys,0))+IFERROR(INDEX(GlazingUpg_Vals,MATCH(H774,GlazingUpg_Keys,0)),0))+INDEX(Hardware_Vals,MATCH("Doors",Hardware_Keys,0)) -> 10471.346 | Q774: =INDEX(Markup_Vals,MATCH("Doors",MarkupCat_Keys,0)) -> 0.4 | R774: =P774*(1+Q774) -> 14659.884 | S774: =R774*(1-TradeDiscount) -> 12900.698 | T774: =R774*(1-VolumeDiscount) -> 11727.908
A775: ALS-SLD-0012 | B775: Doors | C775: Sliding Doors | D775: Aluminium Sliding Door — 2-Panel Slider (1 Fixed + 1 Sliding) — 2409x2009mm — Satin White (RAL 9016) — 6.38mm Laminated Safety | E775: 2-Panel Slider (1 Fixed + 1 Sliding) | F775: 2409x2009mm | G775: Satin White (RAL 9016) | H775: 6.38mm Laminated Safety | I775: Each | J775: Residential/Commercial | K775: Stock | L775: DOOR | M775: 2409 | N775: 2009 | P775: =(M775*N775/1000000)*(INDEX(AreaRate_Vals,MATCH(C775,AreaRate_Keys,0))+IFERROR(INDEX(GlazingUpg_Vals,MATCH(H775,GlazingUpg_Keys,0)),0))+INDEX(Hardware_Vals,MATCH("Doors",Hardware_Keys,0)) -> 10471.346 | Q775: =INDEX(Markup_Vals,MATCH("Doors",MarkupCat_Keys,0)) -> 0.4 | R775: =P775*(1+Q775) -> 14659.884 | S775: =R775*(1-TradeDiscount) -> 12900.698 | T775: =R775*(1-VolumeDiscount) -> 11727.908
... A1313: ALS-PVD-0020 | B1313: Doors | C1313: Pivot Doors | D1313: Aluminium Pivot Entrance Door — 1509x2700mm — Bronze Anodised | E1313: Offset-Pivot, Oversized Entrance | F1313: 1509x2700mm | G1313: Bronze Anodised | H1313: 6.38mm Laminated Safety | I1313: Each | J1313: Commercial/Residential | K1313: Made-to-Order | L1313: DOOR | M1313: 1509 | N1313: 2700 | P1313: =(M1313*N1313/1000000)*(INDEX(AreaRate_Vals,MATCH(C1313,AreaRate_Keys,0))+IFERROR(INDEX(GlazingUpg_Vals,MATCH(H1313,GlazingUpg_Keys,0)),0))+INDEX(Hardware_Vals,MATCH("Doors",Hardware_Keys,0)) -> 14810.05 | Q1313: =INDEX(Markup_Vals,MATCH("Doors",MarkupCat_Keys,0)) -> 0.4 | R1313: =P1313*(1+Q1313) -> 20734.07 | S1313: =R1313*(1-TradeDiscount) -> 18245.982 | T1313: =R1313*(1-VolumeDiscount) -> 16587.256
A1314: ALS-SCD-0001 | B1314: Doors | C1314: Security & Screen Doors | D1314: Aluminium Sliding Security Door (Mesh Infill) — 809x2009mm — Natural Anodised | E1314: Sliding Security Door (Mesh Infill) | F1314: 809x2009mm | G1314: Natural Anodised | H1314: Stainless Security Mesh | I1314: Each | J1314: Residential/Commercial | K1314: Stock | L1314: DOOR | M1314: 809 | N1314: 2009 | P1314: =(M1314*N1314/1000000)*INDEX(AreaRate_Vals,MATCH(C1314,AreaRate_Keys,0))+INDEX(Hardware_Vals,MATCH("Doors",Hardware_Keys,0)) -> 2825.3934 | Q1314: =INDEX(Markup_Vals,MATCH("Doors",MarkupCat_Keys,0)) -> 0.4 | R1314: =P1314*(1+Q1314) -> 3955.5508 | S1314: =R1314*(1-TradeDiscount) -> 3480.8847 | T1314: =R1314*(1-VolumeDiscount) -> 3164.4406
A1315: ALS-SCD-0002 | B1315: Doors | C1315: Security & Screen Doors | D1315: Aluminium Sliding Security Door (Mesh Infill) — 809x2009mm — Satin White (RAL 9016) | E1315: Sliding Security Door (Mesh Infill) | F1315: 809x2009mm | G1315: Satin White (RAL 9016) | H1315: Stainless Security Mesh | I1315: Each | J1315: Residential/Commercial | K1315: Stock | L1315: DOOR | M1315: 809 | N1315: 2009 | P1315: =(M1315*N1315/1000000)*INDEX(AreaRate_Vals,MATCH(C1315,AreaRate_Keys,0))+INDEX(Hardware_Vals,MATCH("Doors",Hardware_Keys,0)) -> 2825.3934 | Q1315: =INDEX(Markup_Vals,MATCH("Doors",MarkupCat_Keys,0)) -> 0.4 | R1315: =P1315*(1+Q1315) -> 3955.5508 | S1315: =R1315*(1-TradeDiscount) -> 3480.8847 | T1315: =R1315*(1-VolumeDiscount) -> 3164.4406
A1316: ALS-SCD-0003 | B1316: Doors | C1316: Security & Screen Doors | D1316: Aluminium Sliding Security Door (Mesh Infill) — 809x2009mm — Charcoal Grey (RAL 7016) | E1316: Sliding Security Door (Mesh Infill) | F1316: 809x2009mm | G1316: Charcoal Grey (RAL 7016) | H1316: Stainless Security Mesh | I1316: Each | J1316: Residential/Commercial | K1316: Stock | L1316: DOOR | M1316: 809 | N1316: 2009 | P1316: =(M1316*N1316/1000000)*INDEX(AreaRate_Vals,MATCH(C1316,AreaRate_Keys,0))+INDEX(Hardware_Vals,MATCH("Doors",Hardware_Keys,0)) -> 2825.3934 | Q1316: =INDEX(Markup_Vals,MATCH("Doors",MarkupCat_Keys,0)) -> 0.4 | R1316: =P1316*(1+Q1316) -> 3955.5508 | S1316: =R1316*(1-TradeDiscount) -> 3480.8847 | T1316: =R1316*(1-VolumeDiscount) -> 3164.4406
A1317: ALS-SCD-0004 | B1317: Doors | C1317: Security & Screen Doors | D1317: Aluminium Sliding Security Door (Mesh Infill) — 909x2009mm — Natural Anodised | E1317: Sliding Security Door (Mesh Infill) | F1317: 909x2009mm | G1317: Natural Anodised | H1317: Stainless Security Mesh | I1317: Each | J1317: Residential/Commercial | K1317: Stock | L1317: DOOR | M1317: 909 | N1317: 2009 | P1317: =(M1317*N1317/1000000)*INDEX(AreaRate_Vals,MATCH(C1317,AreaRate_Keys,0))+INDEX(Hardware_Vals,MATCH("Doors",Hardware_Keys,0)) -> 3106.6534 | Q1317: =INDEX(Markup_Vals,MATCH("Doors",MarkupCat_Keys,0)) -> 0.4 | R1317: =P1317*(1+Q1317) -> 4349.3148 | S1317: =R1317*(1-TradeDiscount) -> 3827.397 | T1317: =R1317*(1-VolumeDiscount) -> 3479.4518
A1318: ALS-SCD-0005 | B1318: Doors | C1318: Security & Screen Doors | D1318: Aluminium Sliding Security Door (Mesh Infill) — 909x2009mm — Satin White (RAL 9016) | E1318: Sliding Security Door (Mesh Infill) | F1318: 909x2009mm | G1318: Satin White (RAL 9016) | H1318: Stainless Security Mesh | I1318: Each | J1318: Residential/Commercial | K1318: Stock | L1318: DOOR | M1318: 909 | N1318: 2009 | P1318: =(M1318*N1318/1000000)*INDEX(AreaRate_Vals,MATCH(C1318,AreaRate_Keys,0))+INDEX(Hardware_Vals,MATCH("Doors",Hardware_Keys,0)) -> 3106.6534 | Q1318: =INDEX(Markup_Vals,MATCH("Doors",MarkupCat_Keys,0)) -> 0.4 | R1318: =P1318*(1+Q1318) -> 4349.3148 | S1318: =R1318*(1-TradeDiscount) -> 3827.397 | T1318: =R1318*(1-VolumeDiscount) -> 3479.4518
A1319: ALS-SCD-0006 | B1319: Doors | C1319: Security & Screen Doors | D1319: Aluminium Sliding Security Door (Mesh Infill) — 909x2009mm — Charcoal Grey (RAL 7016) | E1319: Sliding Security Door (Mesh Infill) | F1319: 909x2009mm | G1319: Charcoal Grey (RAL 7016) | H1319: Stainless Security Mesh | I1319: Each | J1319: Residential/Commercial | K1319: Stock | L1319: DOOR | M1319: 909 | N1319: 2009 | P1319: =(M1319*N1319/1000000)*INDEX(AreaRate_Vals,MATCH(C1319,AreaRate_Keys,0))+INDEX(Hardware_Vals,MATCH("Doors",Hardware_Keys,0)) -> 3106.6534 | Q1319: =INDEX(Markup_Vals,MATCH("Doors",MarkupCat_Keys,0)) -> 0.4 | R1319: =P1319*(1+Q1319) -> 4349.3148 | S1319: =R1319*(1-TradeDiscount) -> 3827.397 | T1319: =R1319*(1-VolumeDiscount) -> 3479.4518
A1320: ALS-SCD-0007 | B1320: Doors | C1320: Security & Screen Doors | D1320: Aluminium Sliding Security Door (Mesh Infill) — 1209x2009mm — Natural Anodised | E1320: Sliding Security Door (Mesh Infill) | F1320: 1209x2009mm | G1320: Natural Anodised | H1320: Stainless Security Mesh | I1320: Each | J1320: Residential/Commercial | K1320: Stock | L1320: DOOR | M1320: 1209 | N1320: 2009 | P1320: =(M1320*N1320/1000000)*INDEX(AreaRate_Vals,MATCH(C1320,AreaRate_Keys,0))+INDEX(Hardware_Vals,MATCH("Doors",Hardware_Keys,0)) -> 3950.4334 | Q1320: =INDEX(Markup_Vals,MATCH("Doors",MarkupCat_Keys,0)) -> 0.4 | R1320: =P1320*(1+Q1320) -> 5530.6068 | S1320: =R1320*(1-TradeDiscount) -> 4866.9339 | T1320: =R1320*(1-VolumeDiscount) -> 4424.4854
A1321: ALS-SCD-0008 | B1321: Doors | C1321: Security & Screen Doors | D1321: Aluminium Sliding Security Door (Mesh Infill) — 1209x2009mm — Satin White (RAL 9016) | E1321: Sliding Security Door (Mesh Infill) | F1321: 1209x2009mm | G1321: Satin White (RAL 9016) | H1321: Stainless Security Mesh | I1321: Each | J1321: Residential/Commercial | K1321: Stock | L1321: DOOR | M1321: 1209 | N1321: 2009 | P1321: =(M1321*N1321/1000000)*INDEX(AreaRate_Vals,MATCH(C1321,AreaRate_Keys,0))+INDEX(Hardware_Vals,MATCH("Doors",Hardware_Keys,0)) -> 3950.4334 | Q1321: =INDEX(Markup_Vals,MATCH("Doors",MarkupCat_Keys,0)) -> 0.4 | R1321: =P1321*(1+Q1321) -> 5530.6068 | S1321: =R1321*(1-TradeDiscount) -> 4866.9339 | T1321: =R1321*(1-VolumeDiscount) -> 4424.4854
A1322: ALS-SCD-0009 | B1322: Doors | C1322: Security & Screen Doors | D1322: Aluminium Sliding Security Door (Mesh Infill) — 1209x2009mm — Charcoal Grey (RAL 7016) | E1322: Sliding Security Door (Mesh Infill) | F1322: 1209x2009mm | G1322: Charcoal Grey (RAL 7016) | H1322: Stainless Security Mesh | I1322: Each | J1322: Residential/Commercial | K1322: Stock | L1322: DOOR | M1322: 1209 | N1322: 2009 | P1322: =(M1322*N1322/1000000)*INDEX(AreaRate_Vals,MATCH(C1322,AreaRate_Keys,0))+INDEX(Hardware_Vals,MATCH("Doors",Hardware_Keys,0)) -> 3950.4334 | Q1322: =INDEX(Markup_Vals,MATCH("Doors",MarkupCat_Keys,0)) -> 0.4 | R1322: =P1322*(1+Q1322) -> 5530.6068 | S1322: =R1322*(1-TradeDiscount) -> 4866.9339 | T1322: =R1322*(1-VolumeDiscount) -> 4424.4854
A1323: ALS-SCD-0010 | B1323: Doors | C1323: Security & Screen Doors | D1323: Aluminium Sliding Security Door (Mesh Infill) — 1809x2009mm — Natural Anodised | E1323: Sliding Security Door (Mesh Infill) | F1323: 1809x2009mm | G1323: Natural Anodised | H1323: Stainless Security Mesh | I1323: Each | J1323: Residential/Commercial | K1323: Stock | L1323: DOOR | M1323: 1809 | N1323: 2009 | P1323: =(M1323*N1323/1000000)*INDEX(AreaRate_Vals,MATCH(C1323,AreaRate_Keys,0))+INDEX(Hardware_Vals,MATCH("Doors",Hardware_Keys,0)) -> 5637.9934 | Q1323: =INDEX(Markup_Vals,MATCH("Doors",MarkupCat_Keys,0)) -> 0.4 | R1323: =P1323*(1+Q1323) -> 7893.1908 | S1323: =R1323*(1-TradeDiscount) -> 6946.0079 | T1323: =R1323*(1-VolumeDiscount) -> 6314.5526
A1324: ALS-SCD-0011 | B1324: Doors | C1324: Security & Screen Doors | D1324: Aluminium Sliding Security Door (Mesh Infill) — 1809x2009mm — Satin White (RAL 9016) | E1324: Sliding Security Door (Mesh Infill) | F1324: 1809x2009mm | G1324: Satin White (RAL 9016) | H1324: Stainless Security Mesh | I1324: Each | J1324: Residential/Commercial | K1324: Stock | L1324: DOOR | M1324: 1809 | N1324: 2009 | P1324: =(M1324*N1324/1000000)*INDEX(AreaRate_Vals,MATCH(C1324,AreaRate_Keys,0))+INDEX(Hardware_Vals,MATCH("Doors",Hardware_Keys,0)) -> 5637.9934 | Q1324: =INDEX(Markup_Vals,MATCH("Doors",MarkupCat_Keys,0)) -> 0.4 | R1324: =P1324*(1+Q1324) -> 7893.1908 | S1324: =R1324*(1-TradeDiscount) -> 6946.0079 | T1324: =R1324*(1-VolumeDiscount) -> 6314.5526
A1325: ALS-SCD-0012 | B1325: Doors | C1325: Security & Screen Doors | D1325: Aluminium Sliding Security Door (Mesh Infill) — 1809x2009mm — Charcoal Grey (RAL 7016) | E1325: Sliding Security Door (Mesh Infill) | F1325: 1809x2009mm | G1325: Charcoal Grey (RAL 7016) | H1325: Stainless Security Mesh | I1325: Each | J1325: Residential/Commercial | K1325: Stock | L1325: DOOR | M1325: 1809 | N1325: 2009 | P1325: =(M1325*N1325/1000000)*INDEX(AreaRate_Vals,MATCH(C1325,AreaRate_Keys,0))+INDEX(Hardware_Vals,MATCH("Doors",Hardware_Keys,0)) -> 5637.9934 | Q1325: =INDEX(Markup_Vals,MATCH("Doors",MarkupCat_Keys,0)) -> 0.4 | R1325: =P1325*(1+Q1325) -> 7893.1908 | S1325: =R1325*(1-TradeDiscount) -> 6946.0079 | T1325: =R1325*(1-VolumeDiscount) -> 6314.5526
... A1367: ALS-SCD-0054 | B1367: Doors | C1367: Security & Screen Doors | D1367: Aluminium Retractable Security Screen Door — 3009x2009mm — Charcoal Grey (RAL 7016) | E1367: Retractable Security Screen Door | F1367: 3009x2009mm | G1367: Charcoal Grey (RAL 7016) | H1367: Stainless Security Mesh | I1367: Each | J1367: Residential/Commercial | K1367: Stock | L1367: DOOR | M1367: 3009 | N1367: 2009 | P1367: =(M1367*N1367/1000000)*INDEX(AreaRate_Vals,MATCH(C1367,AreaRate_Keys,0))+INDEX(Hardware_Vals,MATCH("Doors",Hardware_Keys,0)) -> 9013.1134 | Q1367: =INDEX(Markup_Vals,MATCH("Doors",MarkupCat_Keys,0)) -> 0.4 | R1367: =P1367*(1+Q1367) -> 12618.359 | S1367: =R1367*(1-TradeDiscount) -> 11104.156 | T1367: =R1367*(1-VolumeDiscount) -> 10094.687
A1368: ALS-SFS-0001 | B1368: Facade & Structural Systems | C1368: Shopfront Systems | D1368: Shopfront Framing System — Standard Profile — Natural Anodised | E1368: Shopfront Framing System — Standard Profile | F1368: Custom to Opening | G1368: Natural Anodised | H1368: 4mm Clear Float | I1368: Per Linear Metre | J1368: Commercial/Institutional | K1368: Made-to-Order | P1368: 950 | Q1368: =INDEX(Markup_Vals,MATCH("Facade & Structural Systems",MarkupCat_Keys,0)) -> 0.3 | R1368: =P1368*(1+Q1368) -> 1235 | S1368: =R1368*(1-TradeDiscount) -> 1086.8 | T1368: =R1368*(1-VolumeDiscount) -> 988
A1369: ALS-SFS-0002 | B1369: Facade & Structural Systems | C1369: Shopfront Systems | D1369: Shopfront Framing System — Standard Profile — Satin White (RAL 9016) | E1369: Shopfront Framing System — Standard Profile | F1369: Custom to Opening | G1369: Satin White (RAL 9016) | H1369: 4mm Clear Float | I1369: Per Linear Metre | J1369: Commercial/Institutional | K1369: Made-to-Order | P1369: 950 | Q1369: =INDEX(Markup_Vals,MATCH("Facade & Structural Systems",MarkupCat_Keys,0)) -> 0.3 | R1369: =P1369*(1+Q1369) -> 1235 | S1369: =R1369*(1-TradeDiscount) -> 1086.8 | T1369: =R1369*(1-VolumeDiscount) -> 988
A1370: ALS-SFS-0003 | B1370: Facade & Structural Systems | C1370: Shopfront Systems | D1370: Shopfront Framing System — Standard Profile — Charcoal Grey (RAL 7016) | E1370: Shopfront Framing System — Standard Profile | F1370: Custom to Opening | G1370: Charcoal Grey (RAL 7016) | H1370: 4mm Clear Float | I1370: Per Linear Metre | J1370: Commercial/Institutional | K1370: Made-to-Order | P1370: 950 | Q1370: =INDEX(Markup_Vals,MATCH("Facade & Structural Systems",MarkupCat_Keys,0)) -> 0.3 | R1370: =P1370*(1+Q1370) -> 1235 | S1370: =R1370*(1-TradeDiscount) -> 1086.8 | T1370: =R1370*(1-VolumeDiscount) -> 988
A1371: ALS-SFS-0004 | B1371: Facade & Structural Systems | C1371: Shopfront Systems | D1371: Shopfront Framing System — Standard Profile — Bronze Anodised | E1371: Shopfront Framing System — Standard Profile | F1371: Custom to Opening | G1371: Bronze Anodised | H1371: 4mm Clear Float | I1371: Per Linear Metre | J1371: Commercial/Institutional | K1371: Made-to-Order | P1371: 950 | Q1371: =INDEX(Markup_Vals,MATCH("Facade & Structural Systems",MarkupCat_Keys,0)) -> 0.3 | R1371: =P1371*(1+Q1371) -> 1235 | S1371: =R1371*(1-TradeDiscount) -> 1086.8 | T1371: =R1371*(1-VolumeDiscount) -> 988
A1372: ALS-SFS-0005 | B1372: Facade & Structural Systems | C1372: Shopfront Systems | D1372: Shopfront Framing System — Heavy-Duty Profile — Natural Anodised | E1372: Shopfront Framing System — Heavy-Duty Profile | F1372: Custom to Opening | G1372: Natural Anodised | H1372: 4mm Clear Float | I1372: Per Linear Metre | J1372: Commercial/Institutional | K1372: Made-to-Order | P1372: 1300 | Q1372: =INDEX(Markup_Vals,MATCH("Facade & Structural Systems",MarkupCat_Keys,0)) -> 0.3 | R1372: =P1372*(1+Q1372) -> 1690 | S1372: =R1372*(1-TradeDiscount) -> 1487.2 | T1372: =R1372*(1-VolumeDiscount) -> 1352
A1373: ALS-SFS-0006 | B1373: Facade & Structural Systems | C1373: Shopfront Systems | D1373: Shopfront Framing System — Heavy-Duty Profile — Satin White (RAL 9016) | E1373: Shopfront Framing System — Heavy-Duty Profile | F1373: Custom to Opening | G1373: Satin White (RAL 9016) | H1373: 4mm Clear Float | I1373: Per Linear Metre | J1373: Commercial/Institutional | K1373: Made-to-Order | P1373: 1300 | Q1373: =INDEX(Markup_Vals,MATCH("Facade & Structural Systems",MarkupCat_Keys,0)) -> 0.3 | R1373: =P1373*(1+Q1373) -> 1690 | S1373: =R1373*(1-TradeDiscount) -> 1487.2 | T1373: =R1373*(1-VolumeDiscount) -> 1352
A1374: ALS-SFS-0007 | B1374: Facade & Structural Systems | C1374: Shopfront Systems | D1374: Shopfront Framing System — Heavy-Duty Profile — Charcoal Grey (RAL 7016) | E1374: Shopfront Framing System — Heavy-Duty Profile | F1374: Custom to Opening | G1374: Charcoal Grey (RAL 7016) | H1374: 4mm Clear Float | I1374: Per Linear Metre | J1374: Commercial/Institutional | K1374: Made-to-Order | P1374: 1300 | Q1374: =INDEX(Markup_Vals,MATCH("Facade & Structural Systems",MarkupCat_Keys,0)) -> 0.3 | R1374: =P1374*(1+Q1374) -> 1690 | S1374: =R1374*(1-TradeDiscount) -> 1487.2 | T1374: =R1374*(1-VolumeDiscount) -> 1352
A1375: ALS-SFS-0008 | B1375: Facade & Structural Systems | C1375: Shopfront Systems | D1375: Shopfront Framing System — Heavy-Duty Profile — Bronze Anodised | E1375: Shopfront Framing System — Heavy-Duty Profile | F1375: Custom to Opening | G1375: Bronze Anodised | H1375: 4mm Clear Float | I1375: Per Linear Metre | J1375: Commercial/Institutional | K1375: Made-to-Order | P1375: 1300 | Q1375: =INDEX(Markup_Vals,MATCH("Facade & Structural Systems",MarkupCat_Keys,0)) -> 0.3 | R1375: =P1375*(1+Q1375) -> 1690 | S1375: =R1375*(1-TradeDiscount) -> 1487.2 | T1375: =R1375*(1-VolumeDiscount) -> 1352
A1376: ALS-SFS-0009 | B1376: Facade & Structural Systems | C1376: Shopfront Systems | D1376: Shopfront Entrance Door Unit — Single, Fully-Glazed — Natural Anodised | E1376: Shopfront Entrance Door Unit — Single, Fully-Glazed | F1376: Custom to Opening | G1376: Natural Anodised | H1376: 4mm Clear Float | I1376: Each | J1376: Commercial/Institutional | K1376: Made-to-Order | P1376: 4918 | Q1376: =INDEX(Markup_Vals,MATCH("Facade & Structural Systems",MarkupCat_Keys,0)) -> 0.3 | R1376: =P1376*(1+Q1376) -> 6393.4 | S1376: =R1376*(1-TradeDiscount) -> 5626.192 | T1376: =R1376*(1-VolumeDiscount) -> 5114.72
A1377: ALS-SFS-0010 | B1377: Facade & Structural Systems | C1377: Shopfront Systems | D1377: Shopfront Entrance Door Unit — Single, Fully-Glazed — Satin White (RAL 9016) | E1377: Shopfront Entrance Door Unit — Single, Fully-Glazed | F1377: Custom to Opening | G1377: Satin White (RAL 9016) | H1377: 4mm Clear Float | I1377: Each | J1377: Commercial/Institutional | K1377: Made-to-Order | P1377: 4918 | Q1377: =INDEX(Markup_Vals,MATCH("Facade & Structural Systems",MarkupCat_Keys,0)) -> 0.3 | R1377: =P1377*(1+Q1377) -> 6393.4 | S1377: =R1377*(1-TradeDiscount) -> 5626.192 | T1377: =R1377*(1-VolumeDiscount) -> 5114.72
A1378: ALS-SFS-0011 | B1378: Facade & Structural Systems | C1378: Shopfront Systems | D1378: Shopfront Entrance Door Unit — Single, Fully-Glazed — Charcoal Grey (RAL 7016) | E1378: Shopfront Entrance Door Unit — Single, Fully-Glazed | F1378: Custom to Opening | G1378: Charcoal Grey (RAL 7016) | H1378: 4mm Clear Float | I1378: Each | J1378: Commercial/Institutional | K1378: Made-to-Order | P1378: 4918 | Q1378: =INDEX(Markup_Vals,MATCH("Facade & Structural Systems",MarkupCat_Keys,0)) -> 0.3 | R1378: =P1378*(1+Q1378) -> 6393.4 | S1378: =R1378*(1-TradeDiscount) -> 5626.192 | T1378: =R1378*(1-VolumeDiscount) -> 5114.72
A1379: ALS-SFS-0012 | B1379: Facade & Structural Systems | C1379: Shopfront Systems | D1379: Shopfront Entrance Door Unit — Single, Fully-Glazed — Bronze Anodised | E1379: Shopfront Entrance Door Unit — Single, Fully-Glazed | F1379: Custom to Opening | G1379: Bronze Anodised | H1379: 4mm Clear Float | I1379: Each | J1379: Commercial/Institutional | K1379: Made-to-Order | P1379: 4918 | Q1379: =INDEX(Markup_Vals,MATCH("Facade & Structural Systems",MarkupCat_Keys,0)) -> 0.3 | R1379: =P1379*(1+Q1379) -> 6393.4 | S1379: =R1379*(1-TradeDiscount) -> 5626.192 | T1379: =R1379*(1-VolumeDiscount) -> 5114.72
... A1431: ALS-CWG-0036 | B1431: Facade & Structural Systems | C1431: Curtain Walling & Structural Glazing | D1431: Spider-Fitting Structural Glazing Bracket Set — Solar-Control Tinted IGU — Charcoal Grey (RAL 7016) | E1431: Spider-Fitting Structural Glazing Bracket Set | F1431: Custom to Elevation | G1431: Charcoal Grey (RAL 7016) | H1431: Solar-Control Tinted IGU | I1431: Per Set | J1431: Commercial/Institutional | K1431: CMI Partner Network | P1431: 2800 | Q1431: =INDEX(Markup_Vals,MATCH("Facade & Structural Systems",MarkupCat_Keys,0)) -> 0.3 | R1431: =P1431*(1+Q1431) -> 3640 | S1431: =R1431*(1-TradeDiscount) -> 3203.2 | T1431: =R1431*(1-VolumeDiscount) -> 2912
A1432: ALS-PRG-0001 | B1432: Outdoor Living & Shading | C1432: Pergolas | D1432: Aluminium Fixed-Slat Pergola — 3000x3000mm — Natural Anodised | E1432: Fixed-Slat Pergola | F1432: 3000x3000mm footprint | G1432: Natural Anodised | H1432: N/A | I1432: Each | J1432: Residential/Commercial | K1432: Made-to-Order | L1432: STRUCTURAL | M1432: 3000 | N1432: 3000 | P1432: =(M1432*N1432/1000000)*INDEX(AreaRate_Vals,MATCH(C1432,AreaRate_Keys,0))+IF(H1432="Aluminium Louvre Blade",(M1432*N1432/1000000)*INDEX(Glass_Vals,MATCH("6mm Toughened Louvre Blade",Glass_Keys,0)),0)+INDEX(Hardware_Vals,MATCH("Pergolas",Hardware_Keys,0)) -> 16620 | Q1432: =INDEX(Markup_Vals,MATCH("Outdoor Living & Shading",MarkupCat_Keys,0)) -> 0.45 | R1432: =P1432*(1+Q1432) -> 24099 | S1432: =R1432*(1-TradeDiscount) -> 21207.12 | T1432: =R1432*(1-VolumeDiscount) -> 19279.2
A1433: ALS-PRG-0002 | B1433: Outdoor Living & Shading | C1433: Pergolas | D1433: Aluminium Fixed-Slat Pergola — 3000x3000mm — Satin White (RAL 9016) | E1433: Fixed-Slat Pergola | F1433: 3000x3000mm footprint | G1433: Satin White (RAL 9016) | H1433: N/A | I1433: Each | J1433: Residential/Commercial | K1433: Made-to-Order | L1433: STRUCTURAL | M1433: 3000 | N1433: 3000 | P1433: =(M1433*N1433/1000000)*INDEX(AreaRate_Vals,MATCH(C1433,AreaRate_Keys,0))+IF(H1433="Aluminium Louvre Blade",(M1433*N1433/1000000)*INDEX(Glass_Vals,MATCH("6mm Toughened Louvre Blade",Glass_Keys,0)),0)+INDEX(Hardware_Vals,MATCH("Pergolas",Hardware_Keys,0)) -> 16620 | Q1433: =INDEX(Markup_Vals,MATCH("Outdoor Living & Shading",MarkupCat_Keys,0)) -> 0.45 | R1433: =P1433*(1+Q1433) -> 24099 | S1433: =R1433*(1-TradeDiscount) -> 21207.12 | T1433: =R1433*(1-VolumeDiscount) -> 19279.2
A1434: ALS-PRG-0003 | B1434: Outdoor Living & Shading | C1434: Pergolas | D1434: Aluminium Fixed-Slat Pergola — 3000x3000mm — Charcoal Grey (RAL 7016) | E1434: Fixed-Slat Pergola | F1434: 3000x3000mm footprint | G1434: Charcoal Grey (RAL 7016) | H1434: N/A | I1434: Each | J1434: Residential/Commercial | K1434: Made-to-Order | L1434: STRUCTURAL | M1434: 3000 | N1434: 3000 | P1434: =(M1434*N1434/1000000)*INDEX(AreaRate_Vals,MATCH(C1434,AreaRate_Keys,0))+IF(H1434="Aluminium Louvre Blade",(M1434*N1434/1000000)*INDEX(Glass_Vals,MATCH("6mm Toughened Louvre Blade",Glass_Keys,0)),0)+INDEX(Hardware_Vals,MATCH("Pergolas",Hardware_Keys,0)) -> 16620 | Q1434: =INDEX(Markup_Vals,MATCH("Outdoor Living & Shading",MarkupCat_Keys,0)) -> 0.45 | R1434: =P1434*(1+Q1434) -> 24099 | S1434: =R1434*(1-TradeDiscount) -> 21207.12 | T1434: =R1434*(1-VolumeDiscount) -> 19279.2
A1435: ALS-PRG-0004 | B1435: Outdoor Living & Shading | C1435: Pergolas | D1435: Aluminium Fixed-Slat Pergola — 3000x3000mm — Bronze Anodised | E1435: Fixed-Slat Pergola | F1435: 3000x3000mm footprint | G1435: Bronze Anodised | H1435: N/A | I1435: Each | J1435: Residential/Commercial | K1435: Made-to-Order | L1435: STRUCTURAL | M1435: 3000 | N1435: 3000 | P1435: =(M1435*N1435/1000000)*INDEX(AreaRate_Vals,MATCH(C1435,AreaRate_Keys,0))+IF(H1435="Aluminium Louvre Blade",(M1435*N1435/1000000)*INDEX(Glass_Vals,MATCH("6mm Toughened Louvre Blade",Glass_Keys,0)),0)+INDEX(Hardware_Vals,MATCH("Pergolas",Hardware_Keys,0)) -> 16620 | Q1435: =INDEX(Markup_Vals,MATCH("Outdoor Living & Shading",MarkupCat_Keys,0)) -> 0.45 | R1435: =P1435*(1+Q1435) -> 24099 | S1435: =R1435*(1-TradeDiscount) -> 21207.12 | T1435: =R1435*(1-VolumeDiscount) -> 19279.2
A1436: ALS-PRG-0005 | B1436: Outdoor Living & Shading | C1436: Pergolas | D1436: Aluminium Fixed-Slat Pergola — 3000x4000mm — Natural Anodised | E1436: Fixed-Slat Pergola | F1436: 3000x4000mm footprint | G1436: Natural Anodised | H1436: N/A | I1436: Each | J1436: Residential/Commercial | K1436: Made-to-Order | L1436: STRUCTURAL | M1436: 3000 | N1436: 4000 | P1436: =(M1436*N1436/1000000)*INDEX(AreaRate_Vals,MATCH(C1436,AreaRate_Keys,0))+IF(H1436="Aluminium Louvre Blade",(M1436*N1436/1000000)*INDEX(Glass_Vals,MATCH("6mm Toughened Louvre Blade",Glass_Keys,0)),0)+INDEX(Hardware_Vals,MATCH("Pergolas",Hardware_Keys,0)) -> 22020 | Q1436: =INDEX(Markup_Vals,MATCH("Outdoor Living & Shading",MarkupCat_Keys,0)) -> 0.45 | R1436: =P1436*(1+Q1436) -> 31929 | S1436: =R1436*(1-TradeDiscount) -> 28097.52 | T1436: =R1436*(1-VolumeDiscount) -> 25543.2
A1437: ALS-PRG-0006 | B1437: Outdoor Living & Shading | C1437: Pergolas | D1437: Aluminium Fixed-Slat Pergola — 3000x4000mm — Satin White (RAL 9016) | E1437: Fixed-Slat Pergola | F1437: 3000x4000mm footprint | G1437: Satin White (RAL 9016) | H1437: N/A | I1437: Each | J1437: Residential/Commercial | K1437: Made-to-Order | L1437: STRUCTURAL | M1437: 3000 | N1437: 4000 | P1437: =(M1437*N1437/1000000)*INDEX(AreaRate_Vals,MATCH(C1437,AreaRate_Keys,0))+IF(H1437="Aluminium Louvre Blade",(M1437*N1437/1000000)*INDEX(Glass_Vals,MATCH("6mm Toughened Louvre Blade",Glass_Keys,0)),0)+INDEX(Hardware_Vals,MATCH("Pergolas",Hardware_Keys,0)) -> 22020 | Q1437: =INDEX(Markup_Vals,MATCH("Outdoor Living & Shading",MarkupCat_Keys,0)) -> 0.45 | R1437: =P1437*(1+Q1437) -> 31929 | S1437: =R1437*(1-TradeDiscount) -> 28097.52 | T1437: =R1437*(1-VolumeDiscount) -> 25543.2
A1438: ALS-PRG-0007 | B1438: Outdoor Living & Shading | C1438: Pergolas | D1438: Aluminium Fixed-Slat Pergola — 3000x4000mm — Charcoal Grey (RAL 7016) | E1438: Fixed-Slat Pergola | F1438: 3000x4000mm footprint | G1438: Charcoal Grey (RAL 7016) | H1438: N/A | I1438: Each | J1438: Residential/Commercial | K1438: Made-to-Order | L1438: STRUCTURAL | M1438: 3000 | N1438: 4000 | P1438: =(M1438*N1438/1000000)*INDEX(AreaRate_Vals,MATCH(C1438,AreaRate_Keys,0))+IF(H1438="Aluminium Louvre Blade",(M1438*N1438/1000000)*INDEX(Glass_Vals,MATCH("6mm Toughened Louvre Blade",Glass_Keys,0)),0)+INDEX(Hardware_Vals,MATCH("Pergolas",Hardware_Keys,0)) -> 22020 | Q1438: =INDEX(Markup_Vals,MATCH("Outdoor Living & Shading",MarkupCat_Keys,0)) -> 0.45 | R1438: =P1438*(1+Q1438) -> 31929 | S1438: =R1438*(1-TradeDiscount) -> 28097.52 | T1438: =R1438*(1-VolumeDiscount) -> 25543.2
A1439: ALS-PRG-0008 | B1439: Outdoor Living & Shading | C1439: Pergolas | D1439: Aluminium Fixed-Slat Pergola — 3000x4000mm — Bronze Anodised | E1439: Fixed-Slat Pergola | F1439: 3000x4000mm footprint | G1439: Bronze Anodised | H1439: N/A | I1439: Each | J1439: Residential/Commercial | K1439: Made-to-Order | L1439: STRUCTURAL | M1439: 3000 | N1439: 4000 | P1439: =(M1439*N1439/1000000)*INDEX(AreaRate_Vals,MATCH(C1439,AreaRate_Keys,0))+IF(H1439="Aluminium Louvre Blade",(M1439*N1439/1000000)*INDEX(Glass_Vals,MATCH("6mm Toughened Louvre Blade",Glass_Keys,0)),0)+INDEX(Hardware_Vals,MATCH("Pergolas",Hardware_Keys,0)) -> 22020 | Q1439: =INDEX(Markup_Vals,MATCH("Outdoor Living & Shading",MarkupCat_Keys,0)) -> 0.45 | R1439: =P1439*(1+Q1439) -> 31929 | S1439: =R1439*(1-TradeDiscount) -> 28097.52 | T1439: =R1439*(1-VolumeDiscount) -> 25543.2
A1440: ALS-PRG-0009 | B1440: Outdoor Living & Shading | C1440: Pergolas | D1440: Aluminium Fixed-Slat Pergola — 4000x4000mm — Natural Anodised | E1440: Fixed-Slat Pergola | F1440: 4000x4000mm footprint | G1440: Natural Anodised | H1440: N/A | I1440: Each | J1440: Residential/Commercial | K1440: Made-to-Order | L1440: STRUCTURAL | M1440: 4000 | N1440: 4000 | P1440: =(M1440*N1440/1000000)*INDEX(AreaRate_Vals,MATCH(C1440,AreaRate_Keys,0))+IF(H1440="Aluminium Louvre Blade",(M1440*N1440/1000000)*INDEX(Glass_Vals,MATCH("6mm Toughened Louvre Blade",Glass_Keys,0)),0)+INDEX(Hardware_Vals,MATCH("Pergolas",Hardware_Keys,0)) -> 29220 | Q1440: =INDEX(Markup_Vals,MATCH("Outdoor Living & Shading",MarkupCat_Keys,0)) -> 0.45 | R1440: =P1440*(1+Q1440) -> 42369 | S1440: =R1440*(1-TradeDiscount) -> 37284.72 | T1440: =R1440*(1-VolumeDiscount) -> 33895.2
A1441: ALS-PRG-0010 | B1441: Outdoor Living & Shading | C1441: Pergolas | D1441: Aluminium Fixed-Slat Pergola — 4000x4000mm — Satin White (RAL 9016) | E1441: Fixed-Slat Pergola | F1441: 4000x4000mm footprint | G1441: Satin White (RAL 9016) | H1441: N/A | I1441: Each | J1441: Residential/Commercial | K1441: Made-to-Order | L1441: STRUCTURAL | M1441: 4000 | N1441: 4000 | P1441: =(M1441*N1441/1000000)*INDEX(AreaRate_Vals,MATCH(C1441,AreaRate_Keys,0))+IF(H1441="Aluminium Louvre Blade",(M1441*N1441/1000000)*INDEX(Glass_Vals,MATCH("6mm Toughened Louvre Blade",Glass_Keys,0)),0)+INDEX(Hardware_Vals,MATCH("Pergolas",Hardware_Keys,0)) -> 29220 | Q1441: =INDEX(Markup_Vals,MATCH("Outdoor Living & Shading",MarkupCat_Keys,0)) -> 0.45 | R1441: =P1441*(1+Q1441) -> 42369 | S1441: =R1441*(1-TradeDiscount) -> 37284.72 | T1441: =R1441*(1-VolumeDiscount) -> 33895.2
A1442: ALS-PRG-0011 | B1442: Outdoor Living & Shading | C1442: Pergolas | D1442: Aluminium Fixed-Slat Pergola — 4000x4000mm — Charcoal Grey (RAL 7016) | E1442: Fixed-Slat Pergola | F1442: 4000x4000mm footprint | G1442: Charcoal Grey (RAL 7016) | H1442: N/A | I1442: Each | J1442: Residential/Commercial | K1442: Made-to-Order | L1442: STRUCTURAL | M1442: 4000 | N1442: 4000 | P1442: =(M1442*N1442/1000000)*INDEX(AreaRate_Vals,MATCH(C1442,AreaRate_Keys,0))+IF(H1442="Aluminium Louvre Blade",(M1442*N1442/1000000)*INDEX(Glass_Vals,MATCH("6mm Toughened Louvre Blade",Glass_Keys,0)),0)+INDEX(Hardware_Vals,MATCH("Pergolas",Hardware_Keys,0)) -> 29220 | Q1442: =INDEX(Markup_Vals,MATCH("Outdoor Living & Shading",MarkupCat_Keys,0)) -> 0.45 | R1442: =P1442*(1+Q1442) -> 42369 | S1442: =R1442*(1-TradeDiscount) -> 37284.72 | T1442: =R1442*(1-VolumeDiscount) -> 33895.2
A1443: ALS-PRG-0012 | B1443: Outdoor Living & Shading | C1443: Pergolas | D1443: Aluminium Fixed-Slat Pergola — 4000x4000mm — Bronze Anodised | E1443: Fixed-Slat Pergola | F1443: 4000x4000mm footprint | G1443: Bronze Anodised | H1443: N/A | I1443: Each | J1443: Residential/Commercial | K1443: Made-to-Order | L1443: STRUCTURAL | M1443: 4000 | N1443: 4000 | P1443: =(M1443*N1443/1000000)*INDEX(AreaRate_Vals,MATCH(C1443,AreaRate_Keys,0))+IF(H1443="Aluminium Louvre Blade",(M1443*N1443/1000000)*INDEX(Glass_Vals,MATCH("6mm Toughened Louvre Blade",Glass_Keys,0)),0)+INDEX(Hardware_Vals,MATCH("Pergolas",Hardware_Keys,0)) -> 29220 | Q1443: =INDEX(Markup_Vals,MATCH("Outdoor Living & Shading",MarkupCat_Keys,0)) -> 0.45 | R1443: =P1443*(1+Q1443) -> 42369 | S1443: =R1443*(1-TradeDiscount) -> 37284.72 | T1443: =R1443*(1-VolumeDiscount) -> 33895.2
... A1527: ALS-PRG-0096 | B1527: Outdoor Living & Shading | C1527: Pergolas | D1527: Aluminium Gable-Roof Pergola — 6000x4000mm — Bronze Anodised | E1527: Gable-Roof Pergola | F1527: 6000x4000mm footprint | G1527: Bronze Anodised | H1527: N/A | I1527: Each | J1527: Residential/Commercial | K1527: Made-to-Order | L1527: STRUCTURAL | M1527: 6000 | N1527: 4000 | P1527: =(M1527*N1527/1000000)*INDEX(AreaRate_Vals,MATCH(C1527,AreaRate_Keys,0))+IF(H1527="Aluminium Louvre Blade",(M1527*N1527/1000000)*INDEX(Glass_Vals,MATCH("6mm Toughened Louvre Blade",Glass_Keys,0)),0)+INDEX(Hardware_Vals,MATCH("Pergolas",Hardware_Keys,0)) -> 43620 | Q1527: =INDEX(Markup_Vals,MATCH("Outdoor Living & Shading",MarkupCat_Keys,0)) -> 0.45 | R1527: =P1527*(1+Q1527) -> 63249 | S1527: =R1527*(1-TradeDiscount) -> 55659.12 | T1527: =R1527*(1-VolumeDiscount) -> 50599.2
A1528: ALS-CPT-0001 | B1528: Outdoor Living & Shading | C1528: Carports & Canopies | D1528: Aluminium Single-Bay Flat Carport — 3000x5500mm — Natural Anodised | E1528: Single-Bay Flat Carport | F1528: 3000x5500mm footprint | G1528: Natural Anodised | H1528: N/A | I1528: Each | J1528: Residential/Commercial | K1528: Made-to-Order | L1528: STRUCTURAL | M1528: 3000 | N1528: 5500 | P1528: =(M1528*N1528/1000000)*INDEX(AreaRate_Vals,MATCH(C1528,AreaRate_Keys,0))+IF(H1528="Aluminium Louvre Blade",(M1528*N1528/1000000)*INDEX(Glass_Vals,MATCH("6mm Toughened Louvre Blade",Glass_Keys,0)),0)+INDEX(Hardware_Vals,MATCH("Carports & Canopies",Hardware_Keys,0)) -> 26900 | Q1528: =INDEX(Markup_Vals,MATCH("Outdoor Living & Shading",MarkupCat_Keys,0)) -> 0.45 | R1528: =P1528*(1+Q1528) -> 39005 | S1528: =R1528*(1-TradeDiscount) -> 34324.4 | T1528: =R1528*(1-VolumeDiscount) -> 31204
A1529: ALS-CPT-0002 | B1529: Outdoor Living & Shading | C1529: Carports & Canopies | D1529: Aluminium Single-Bay Flat Carport — 3000x5500mm — Satin White (RAL 9016) | E1529: Single-Bay Flat Carport | F1529: 3000x5500mm footprint | G1529: Satin White (RAL 9016) | H1529: N/A | I1529: Each | J1529: Residential/Commercial | K1529: Made-to-Order | L1529: STRUCTURAL | M1529: 3000 | N1529: 5500 | P1529: =(M1529*N1529/1000000)*INDEX(AreaRate_Vals,MATCH(C1529,AreaRate_Keys,0))+IF(H1529="Aluminium Louvre Blade",(M1529*N1529/1000000)*INDEX(Glass_Vals,MATCH("6mm Toughened Louvre Blade",Glass_Keys,0)),0)+INDEX(Hardware_Vals,MATCH("Carports & Canopies",Hardware_Keys,0)) -> 26900 | Q1529: =INDEX(Markup_Vals,MATCH("Outdoor Living & Shading",MarkupCat_Keys,0)) -> 0.45 | R1529: =P1529*(1+Q1529) -> 39005 | S1529: =R1529*(1-TradeDiscount) -> 34324.4 | T1529: =R1529*(1-VolumeDiscount) -> 31204
A1530: ALS-CPT-0003 | B1530: Outdoor Living & Shading | C1530: Carports & Canopies | D1530: Aluminium Single-Bay Flat Carport — 3000x5500mm — Charcoal Grey (RAL 7016) | E1530: Single-Bay Flat Carport | F1530: 3000x5500mm footprint | G1530: Charcoal Grey (RAL 7016) | H1530: N/A | I1530: Each | J1530: Residential/Commercial | K1530: Made-to-Order | L1530: STRUCTURAL | M1530: 3000 | N1530: 5500 | P1530: =(M1530*N1530/1000000)*INDEX(AreaRate_Vals,MATCH(C1530,AreaRate_Keys,0))+IF(H1530="Aluminium Louvre Blade",(M1530*N1530/1000000)*INDEX(Glass_Vals,MATCH("6mm Toughened Louvre Blade",Glass_Keys,0)),0)+INDEX(Hardware_Vals,MATCH("Carports & Canopies",Hardware_Keys,0)) -> 26900 | Q1530: =INDEX(Markup_Vals,MATCH("Outdoor Living & Shading",MarkupCat_Keys,0)) -> 0.45 | R1530: =P1530*(1+Q1530) -> 39005 | S1530: =R1530*(1-TradeDiscount) -> 34324.4 | T1530: =R1530*(1-VolumeDiscount) -> 31204
A1531: ALS-CPT-0004 | B1531: Outdoor Living & Shading | C1531: Carports & Canopies | D1531: Aluminium Single-Bay Flat Carport — 3000x6000mm — Natural Anodised | E1531: Single-Bay Flat Carport | F1531: 3000x6000mm footprint | G1531: Natural Anodised | H1531: N/A | I1531: Each | J1531: Residential/Commercial | K1531: Made-to-Order | L1531: STRUCTURAL | M1531: 3000 | N1531: 6000 | P1531: =(M1531*N1531/1000000)*INDEX(AreaRate_Vals,MATCH(C1531,AreaRate_Keys,0))+IF(H1531="Aluminium Louvre Blade",(M1531*N1531/1000000)*INDEX(Glass_Vals,MATCH("6mm Toughened Louvre Blade",Glass_Keys,0)),0)+INDEX(Hardware_Vals,MATCH("Carports & Canopies",Hardware_Keys,0)) -> 29300 | Q1531: =INDEX(Markup_Vals,MATCH("Outdoor Living & Shading",MarkupCat_Keys,0)) -> 0.45 | R1531: =P1531*(1+Q1531) -> 42485 | S1531: =R1531*(1-TradeDiscount) -> 37386.8 | T1531: =R1531*(1-VolumeDiscount) -> 33988
A1532: ALS-CPT-0005 | B1532: Outdoor Living & Shading | C1532: Carports & Canopies | D1532: Aluminium Single-Bay Flat Carport — 3000x6000mm — Satin White (RAL 9016) | E1532: Single-Bay Flat Carport | F1532: 3000x6000mm footprint | G1532: Satin White (RAL 9016) | H1532: N/A | I1532: Each | J1532: Residential/Commercial | K1532: Made-to-Order | L1532: STRUCTURAL | M1532: 3000 | N1532: 6000 | P1532: =(M1532*N1532/1000000)*INDEX(AreaRate_Vals,MATCH(C1532,AreaRate_Keys,0))+IF(H1532="Aluminium Louvre Blade",(M1532*N1532/1000000)*INDEX(Glass_Vals,MATCH("6mm Toughened Louvre Blade",Glass_Keys,0)),0)+INDEX(Hardware_Vals,MATCH("Carports & Canopies",Hardware_Keys,0)) -> 29300 | Q1532: =INDEX(Markup_Vals,MATCH("Outdoor Living & Shading",MarkupCat_Keys,0)) -> 0.45 | R1532: =P1532*(1+Q1532) -> 42485 | S1532: =R1532*(1-TradeDiscount) -> 37386.8 | T1532: =R1532*(1-VolumeDiscount) -> 33988
A1533: ALS-CPT-0006 | B1533: Outdoor Living & Shading | C1533: Carports & Canopies | D1533: Aluminium Single-Bay Flat Carport — 3000x6000mm — Charcoal Grey (RAL 7016) | E1533: Single-Bay Flat Carport | F1533: 3000x6000mm footprint | G1533: Charcoal Grey (RAL 7016) | H1533: N/A | I1533: Each | J1533: Residential/Commercial | K1533: Made-to-Order | L1533: STRUCTURAL | M1533: 3000 | N1533: 6000 | P1533: =(M1533*N1533/1000000)*INDEX(AreaRate_Vals,MATCH(C1533,AreaRate_Keys,0))+IF(H1533="Aluminium Louvre Blade",(M1533*N1533/1000000)*INDEX(Glass_Vals,MATCH("6mm Toughened Louvre Blade",Glass_Keys,0)),0)+INDEX(Hardware_Vals,MATCH("Carports & Canopies",Hardware_Keys,0)) -> 29300 | Q1533: =INDEX(Markup_Vals,MATCH("Outdoor Living & Shading",MarkupCat_Keys,0)) -> 0.45 | R1533: =P1533*(1+Q1533) -> 42485 | S1533: =R1533*(1-TradeDiscount) -> 37386.8 | T1533: =R1533*(1-VolumeDiscount) -> 33988
A1534: ALS-CPT-0007 | B1534: Outdoor Living & Shading | C1534: Carports & Canopies | D1534: Aluminium Single-Bay Flat Carport — 5500x5500mm — Natural Anodised | E1534: Single-Bay Flat Carport | F1534: 5500x5500mm footprint | G1534: Natural Anodised | H1534: N/A | I1534: Each | J1534: Residential/Commercial | K1534: Made-to-Order | L1534: STRUCTURAL | M1534: 5500 | N1534: 5500 | P1534: =(M1534*N1534/1000000)*INDEX(AreaRate_Vals,MATCH(C1534,AreaRate_Keys,0))+IF(H1534="Aluminium Louvre Blade",(M1534*N1534/1000000)*INDEX(Glass_Vals,MATCH("6mm Toughened Louvre Blade",Glass_Keys,0)),0)+INDEX(Hardware_Vals,MATCH("Carports & Canopies",Hardware_Keys,0)) -> 48900 | Q1534: =INDEX(Markup_Vals,MATCH("Outdoor Living & Shading",MarkupCat_Keys,0)) -> 0.45 | R1534: =P1534*(1+Q1534) -> 70905 | S1534: =R1534*(1-TradeDiscount) -> 62396.4 | T1534: =R1534*(1-VolumeDiscount) -> 56724
A1535: ALS-CPT-0008 | B1535: Outdoor Living & Shading | C1535: Carports & Canopies | D1535: Aluminium Single-Bay Flat Carport — 5500x5500mm — Satin White (RAL 9016) | E1535: Single-Bay Flat Carport | F1535: 5500x5500mm footprint | G1535: Satin White (RAL 9016) | H1535: N/A | I1535: Each | J1535: Residential/Commercial | K1535: Made-to-Order | L1535: STRUCTURAL | M1535: 5500 | N1535: 5500 | P1535: =(M1535*N1535/1000000)*INDEX(AreaRate_Vals,MATCH(C1535,AreaRate_Keys,0))+IF(H1535="Aluminium Louvre Blade",(M1535*N1535/1000000)*INDEX(Glass_Vals,MATCH("6mm Toughened Louvre Blade",Glass_Keys,0)),0)+INDEX(Hardware_Vals,MATCH("Carports & Canopies",Hardware_Keys,0)) -> 48900 | Q1535: =INDEX(Markup_Vals,MATCH("Outdoor Living & Shading",MarkupCat_Keys,0)) -> 0.45 | R1535: =P1535*(1+Q1535) -> 70905 | S1535: =R1535*(1-TradeDiscount) -> 62396.4 | T1535: =R1535*(1-VolumeDiscount) -> 56724
A1536: ALS-CPT-0009 | B1536: Outdoor Living & Shading | C1536: Carports & Canopies | D1536: Aluminium Single-Bay Flat Carport — 5500x5500mm — Charcoal Grey (RAL 7016) | E1536: Single-Bay Flat Carport | F1536: 5500x5500mm footprint | G1536: Charcoal Grey (RAL 7016) | H1536: N/A | I1536: Each | J1536: Residential/Commercial | K1536: Made-to-Order | L1536: STRUCTURAL | M1536: 5500 | N1536: 5500 | P1536: =(M1536*N1536/1000000)*INDEX(AreaRate_Vals,MATCH(C1536,AreaRate_Keys,0))+IF(H1536="Aluminium Louvre Blade",(M1536*N1536/1000000)*INDEX(Glass_Vals,MATCH("6mm Toughened Louvre Blade",Glass_Keys,0)),0)+INDEX(Hardware_Vals,MATCH("Carports & Canopies",Hardware_Keys,0)) -> 48900 | Q1536: =INDEX(Markup_Vals,MATCH("Outdoor Living & Shading",MarkupCat_Keys,0)) -> 0.45 | R1536: =P1536*(1+Q1536) -> 70905 | S1536: =R1536*(1-TradeDiscount) -> 62396.4 | T1536: =R1536*(1-VolumeDiscount) -> 56724
A1537: ALS-CPT-0010 | B1537: Outdoor Living & Shading | C1537: Carports & Canopies | D1537: Aluminium Single-Bay Flat Carport — 6000x6000mm — Natural Anodised | E1537: Single-Bay Flat Carport | F1537: 6000x6000mm footprint | G1537: Natural Anodised | H1537: N/A | I1537: Each | J1537: Residential/Commercial | K1537: Made-to-Order | L1537: STRUCTURAL | M1537: 6000 | N1537: 6000 | P1537: =(M1537*N1537/1000000)*INDEX(AreaRate_Vals,MATCH(C1537,AreaRate_Keys,0))+IF(H1537="Aluminium Louvre Blade",(M1537*N1537/1000000)*INDEX(Glass_Vals,MATCH("6mm Toughened Louvre Blade",Glass_Keys,0)),0)+INDEX(Hardware_Vals,MATCH("Carports & Canopies",Hardware_Keys,0)) -> 58100 | Q1537: =INDEX(Markup_Vals,MATCH("Outdoor Living & Shading",MarkupCat_Keys,0)) -> 0.45 | R1537: =P1537*(1+Q1537) -> 84245 | S1537: =R1537*(1-TradeDiscount) -> 74135.6 | T1537: =R1537*(1-VolumeDiscount) -> 67396
A1538: ALS-CPT-0011 | B1538: Outdoor Living & Shading | C1538: Carports & Canopies | D1538: Aluminium Single-Bay Flat Carport — 6000x6000mm — Satin White (RAL 9016) | E1538: Single-Bay Flat Carport | F1538: 6000x6000mm footprint | G1538: Satin White (RAL 9016) | H1538: N/A | I1538: Each | J1538: Residential/Commercial | K1538: Made-to-Order | L1538: STRUCTURAL | M1538: 6000 | N1538: 6000 | P1538: =(M1538*N1538/1000000)*INDEX(AreaRate_Vals,MATCH(C1538,AreaRate_Keys,0))+IF(H1538="Aluminium Louvre Blade",(M1538*N1538/1000000)*INDEX(Glass_Vals,MATCH("6mm Toughened Louvre Blade",Glass_Keys,0)),0)+INDEX(Hardware_Vals,MATCH("Carports & Canopies",Hardware_Keys,0)) -> 58100 | Q1538: =INDEX(Markup_Vals,MATCH("Outdoor Living & Shading",MarkupCat_Keys,0)) -> 0.45 | R1538: =P1538*(1+Q1538) -> 84245 | S1538: =R1538*(1-TradeDiscount) -> 74135.6 | T1538: =R1538*(1-VolumeDiscount) -> 67396
A1539: ALS-CPT-0012 | B1539: Outdoor Living & Shading | C1539: Carports & Canopies | D1539: Aluminium Single-Bay Flat Carport — 6000x6000mm — Charcoal Grey (RAL 7016) | E1539: Single-Bay Flat Carport | F1539: 6000x6000mm footprint | G1539: Charcoal Grey (RAL 7016) | H1539: N/A | I1539: Each | J1539: Residential/Commercial | K1539: Made-to-Order | L1539: STRUCTURAL | M1539: 6000 | N1539: 6000 | P1539: =(M1539*N1539/1000000)*INDEX(AreaRate_Vals,MATCH(C1539,AreaRate_Keys,0))+IF(H1539="Aluminium Louvre Blade",(M1539*N1539/1000000)*INDEX(Glass_Vals,MATCH("6mm Toughened Louvre Blade",Glass_Keys,0)),0)+INDEX(Hardware_Vals,MATCH("Carports & Canopies",Hardware_Keys,0)) -> 58100 | Q1539: =INDEX(Markup_Vals,MATCH("Outdoor Living & Shading",MarkupCat_Keys,0)) -> 0.45 | R1539: =P1539*(1+Q1539) -> 84245 | S1539: =R1539*(1-TradeDiscount) -> 74135.6 | T1539: =R1539*(1-VolumeDiscount) -> 67396
... A1572: ALS-CPT-0045 | B1572: Outdoor Living & Shading | C1572: Carports & Canopies | D1572: Aluminium Curved-Roof Carport Canopy — 6000x7000mm — Charcoal Grey (RAL 7016) | E1572: Curved-Roof Carport Canopy | F1572: 6000x7000mm footprint | G1572: Charcoal Grey (RAL 7016) | H1572: N/A | I1572: Each | J1572: Residential/Commercial | K1572: Made-to-Order | L1572: STRUCTURAL | M1572: 6000 | N1572: 7000 | P1572: =(M1572*N1572/1000000)*INDEX(AreaRate_Vals,MATCH(C1572,AreaRate_Keys,0))+IF(H1572="Aluminium Louvre Blade",(M1572*N1572/1000000)*INDEX(Glass_Vals,MATCH("6mm Toughened Louvre Blade",Glass_Keys,0)),0)+INDEX(Hardware_Vals,MATCH("Carports & Canopies",Hardware_Keys,0)) -> 67700 | Q1572: =INDEX(Markup_Vals,MATCH("Outdoor Living & Shading",MarkupCat_Keys,0)) -> 0.45 | R1572: =P1572*(1+Q1572) -> 98165 | S1572: =R1572*(1-TradeDiscount) -> 86385.2 | T1572: =R1572*(1-VolumeDiscount) -> 78532
A1573: ALS-AWN-0001 | B1573: Outdoor Living & Shading | C1573: Awnings & Canopy Shading | D1573: Retractable Fabric Awning, Aluminium Cassette — 2000x1500mm — Natural Anodised | E1573: Retractable Fabric Awning, Aluminium Cassette | F1573: 2000x1500mm | G1573: Natural Anodised | H1573: N/A | I1573: Each | J1573: Residential/Commercial | K1573: Made-to-Order | L1573: LIGHT | M1573: 2000 | N1573: 1500 | P1573: =(M1573*N1573/1000000)*INDEX(AreaRate_Vals,MATCH(C1573,AreaRate_Keys,0))+INDEX(Hardware_Vals,MATCH("Awnings & Canopy Shading",Hardware_Keys,0)) -> 3950 | Q1573: =INDEX(Markup_Vals,MATCH("Outdoor Living & Shading",MarkupCat_Keys,0)) -> 0.45 | R1573: =P1573*(1+Q1573) -> 5727.5 | S1573: =R1573*(1-TradeDiscount) -> 5040.2 | T1573: =R1573*(1-VolumeDiscount) -> 4582
A1574: ALS-AWN-0002 | B1574: Outdoor Living & Shading | C1574: Awnings & Canopy Shading | D1574: Retractable Fabric Awning, Aluminium Cassette — 2000x1500mm — Satin White (RAL 9016) | E1574: Retractable Fabric Awning, Aluminium Cassette | F1574: 2000x1500mm | G1574: Satin White (RAL 9016) | H1574: N/A | I1574: Each | J1574: Residential/Commercial | K1574: Made-to-Order | L1574: LIGHT | M1574: 2000 | N1574: 1500 | P1574: =(M1574*N1574/1000000)*INDEX(AreaRate_Vals,MATCH(C1574,AreaRate_Keys,0))+INDEX(Hardware_Vals,MATCH("Awnings & Canopy Shading",Hardware_Keys,0)) -> 3950 | Q1574: =INDEX(Markup_Vals,MATCH("Outdoor Living & Shading",MarkupCat_Keys,0)) -> 0.45 | R1574: =P1574*(1+Q1574) -> 5727.5 | S1574: =R1574*(1-TradeDiscount) -> 5040.2 | T1574: =R1574*(1-VolumeDiscount) -> 4582
A1575: ALS-AWN-0003 | B1575: Outdoor Living & Shading | C1575: Awnings & Canopy Shading | D1575: Retractable Fabric Awning, Aluminium Cassette — 2000x1500mm — Charcoal Grey (RAL 7016) | E1575: Retractable Fabric Awning, Aluminium Cassette | F1575: 2000x1500mm | G1575: Charcoal Grey (RAL 7016) | H1575: N/A | I1575: Each | J1575: Residential/Commercial | K1575: Made-to-Order | L1575: LIGHT | M1575: 2000 | N1575: 1500 | P1575: =(M1575*N1575/1000000)*INDEX(AreaRate_Vals,MATCH(C1575,AreaRate_Keys,0))+INDEX(Hardware_Vals,MATCH("Awnings & Canopy Shading",Hardware_Keys,0)) -> 3950 | Q1575: =INDEX(Markup_Vals,MATCH("Outdoor Living & Shading",MarkupCat_Keys,0)) -> 0.45 | R1575: =P1575*(1+Q1575) -> 5727.5 | S1575: =R1575*(1-TradeDiscount) -> 5040.2 | T1575: =R1575*(1-VolumeDiscount) -> 4582
A1576: ALS-AWN-0004 | B1576: Outdoor Living & Shading | C1576: Awnings & Canopy Shading | D1576: Retractable Fabric Awning, Aluminium Cassette — 3000x2000mm — Natural Anodised | E1576: Retractable Fabric Awning, Aluminium Cassette | F1576: 3000x2000mm | G1576: Natural Anodised | H1576: N/A | I1576: Each | J1576: Residential/Commercial | K1576: Made-to-Order | L1576: LIGHT | M1576: 3000 | N1576: 2000 | P1576: =(M1576*N1576/1000000)*INDEX(AreaRate_Vals,MATCH(C1576,AreaRate_Keys,0))+INDEX(Hardware_Vals,MATCH("Awnings & Canopy Shading",Hardware_Keys,0)) -> 7550 | Q1576: =INDEX(Markup_Vals,MATCH("Outdoor Living & Shading",MarkupCat_Keys,0)) -> 0.45 | R1576: =P1576*(1+Q1576) -> 10947.5 | S1576: =R1576*(1-TradeDiscount) -> 9633.8 | T1576: =R1576*(1-VolumeDiscount) -> 8758
A1577: ALS-AWN-0005 | B1577: Outdoor Living & Shading | C1577: Awnings & Canopy Shading | D1577: Retractable Fabric Awning, Aluminium Cassette — 3000x2000mm — Satin White (RAL 9016) | E1577: Retractable Fabric Awning, Aluminium Cassette | F1577: 3000x2000mm | G1577: Satin White (RAL 9016) | H1577: N/A | I1577: Each | J1577: Residential/Commercial | K1577: Made-to-Order | L1577: LIGHT | M1577: 3000 | N1577: 2000 | P1577: =(M1577*N1577/1000000)*INDEX(AreaRate_Vals,MATCH(C1577,AreaRate_Keys,0))+INDEX(Hardware_Vals,MATCH("Awnings & Canopy Shading",Hardware_Keys,0)) -> 7550 | Q1577: =INDEX(Markup_Vals,MATCH("Outdoor Living & Shading",MarkupCat_Keys,0)) -> 0.45 | R1577: =P1577*(1+Q1577) -> 10947.5 | S1577: =R1577*(1-TradeDiscount) -> 9633.8 | T1577: =R1577*(1-VolumeDiscount) -> 8758
A1578: ALS-AWN-0006 | B1578: Outdoor Living & Shading | C1578: Awnings & Canopy Shading | D1578: Retractable Fabric Awning, Aluminium Cassette — 3000x2000mm — Charcoal Grey (RAL 7016) | E1578: Retractable Fabric Awning, Aluminium Cassette | F1578: 3000x2000mm | G1578: Charcoal Grey (RAL 7016) | H1578: N/A | I1578: Each | J1578: Residential/Commercial | K1578: Made-to-Order | L1578: LIGHT | M1578: 3000 | N1578: 2000 | P1578: =(M1578*N1578/1000000)*INDEX(AreaRate_Vals,MATCH(C1578,AreaRate_Keys,0))+INDEX(Hardware_Vals,MATCH("Awnings & Canopy Shading",Hardware_Keys,0)) -> 7550 | Q1578: =INDEX(Markup_Vals,MATCH("Outdoor Living & Shading",MarkupCat_Keys,0)) -> 0.45 | R1578: =P1578*(1+Q1578) -> 10947.5 | S1578: =R1578*(1-TradeDiscount) -> 9633.8 | T1578: =R1578*(1-VolumeDiscount) -> 8758
A1579: ALS-AWN-0007 | B1579: Outdoor Living & Shading | C1579: Awnings & Canopy Shading | D1579: Retractable Fabric Awning, Aluminium Cassette — 4000x2500mm — Natural Anodised | E1579: Retractable Fabric Awning, Aluminium Cassette | F1579: 4000x2500mm | G1579: Natural Anodised | H1579: N/A | I1579: Each | J1579: Residential/Commercial | K1579: Made-to-Order | L1579: LIGHT | M1579: 4000 | N1579: 2500 | P1579: =(M1579*N1579/1000000)*INDEX(AreaRate_Vals,MATCH(C1579,AreaRate_Keys,0))+INDEX(Hardware_Vals,MATCH("Awnings & Canopy Shading",Hardware_Keys,0)) -> 12350 | Q1579: =INDEX(Markup_Vals,MATCH("Outdoor Living & Shading",MarkupCat_Keys,0)) -> 0.45 | R1579: =P1579*(1+Q1579) -> 17907.5 | S1579: =R1579*(1-TradeDiscount) -> 15758.6 | T1579: =R1579*(1-VolumeDiscount) -> 14326
A1580: ALS-AWN-0008 | B1580: Outdoor Living & Shading | C1580: Awnings & Canopy Shading | D1580: Retractable Fabric Awning, Aluminium Cassette — 4000x2500mm — Satin White (RAL 9016) | E1580: Retractable Fabric Awning, Aluminium Cassette | F1580: 4000x2500mm | G1580: Satin White (RAL 9016) | H1580: N/A | I1580: Each | J1580: Residential/Commercial | K1580: Made-to-Order | L1580: LIGHT | M1580: 4000 | N1580: 2500 | P1580: =(M1580*N1580/1000000)*INDEX(AreaRate_Vals,MATCH(C1580,AreaRate_Keys,0))+INDEX(Hardware_Vals,MATCH("Awnings & Canopy Shading",Hardware_Keys,0)) -> 12350 | Q1580: =INDEX(Markup_Vals,MATCH("Outdoor Living & Shading",MarkupCat_Keys,0)) -> 0.45 | R1580: =P1580*(1+Q1580) -> 17907.5 | S1580: =R1580*(1-TradeDiscount) -> 15758.6 | T1580: =R1580*(1-VolumeDiscount) -> 14326
A1581: ALS-AWN-0009 | B1581: Outdoor Living & Shading | C1581: Awnings & Canopy Shading | D1581: Retractable Fabric Awning, Aluminium Cassette — 4000x2500mm — Charcoal Grey (RAL 7016) | E1581: Retractable Fabric Awning, Aluminium Cassette | F1581: 4000x2500mm | G1581: Charcoal Grey (RAL 7016) | H1581: N/A | I1581: Each | J1581: Residential/Commercial | K1581: Made-to-Order | L1581: LIGHT | M1581: 4000 | N1581: 2500 | P1581: =(M1581*N1581/1000000)*INDEX(AreaRate_Vals,MATCH(C1581,AreaRate_Keys,0))+INDEX(Hardware_Vals,MATCH("Awnings & Canopy Shading",Hardware_Keys,0)) -> 12350 | Q1581: =INDEX(Markup_Vals,MATCH("Outdoor Living & Shading",MarkupCat_Keys,0)) -> 0.45 | R1581: =P1581*(1+Q1581) -> 17907.5 | S1581: =R1581*(1-TradeDiscount) -> 15758.6 | T1581: =R1581*(1-VolumeDiscount) -> 14326
A1582: ALS-AWN-0010 | B1582: Outdoor Living & Shading | C1582: Awnings & Canopy Shading | D1582: Retractable Fabric Awning, Aluminium Cassette — 5000x3000mm — Natural Anodised | E1582: Retractable Fabric Awning, Aluminium Cassette | F1582: 5000x3000mm | G1582: Natural Anodised | H1582: N/A | I1582: Each | J1582: Residential/Commercial | K1582: Made-to-Order | L1582: LIGHT | M1582: 5000 | N1582: 3000 | P1582: =(M1582*N1582/1000000)*INDEX(AreaRate_Vals,MATCH(C1582,AreaRate_Keys,0))+INDEX(Hardware_Vals,MATCH("Awnings & Canopy Shading",Hardware_Keys,0)) -> 18350 | Q1582: =INDEX(Markup_Vals,MATCH("Outdoor Living & Shading",MarkupCat_Keys,0)) -> 0.45 | R1582: =P1582*(1+Q1582) -> 26607.5 | S1582: =R1582*(1-TradeDiscount) -> 23414.6 | T1582: =R1582*(1-VolumeDiscount) -> 21286
A1583: ALS-AWN-0011 | B1583: Outdoor Living & Shading | C1583: Awnings & Canopy Shading | D1583: Retractable Fabric Awning, Aluminium Cassette — 5000x3000mm — Satin White (RAL 9016) | E1583: Retractable Fabric Awning, Aluminium Cassette | F1583: 5000x3000mm | G1583: Satin White (RAL 9016) | H1583: N/A | I1583: Each | J1583: Residential/Commercial | K1583: Made-to-Order | L1583: LIGHT | M1583: 5000 | N1583: 3000 | P1583: =(M1583*N1583/1000000)*INDEX(AreaRate_Vals,MATCH(C1583,AreaRate_Keys,0))+INDEX(Hardware_Vals,MATCH("Awnings & Canopy Shading",Hardware_Keys,0)) -> 18350 | Q1583: =INDEX(Markup_Vals,MATCH("Outdoor Living & Shading",MarkupCat_Keys,0)) -> 0.45 | R1583: =P1583*(1+Q1583) -> 26607.5 | S1583: =R1583*(1-TradeDiscount) -> 23414.6 | T1583: =R1583*(1-VolumeDiscount) -> 21286
A1584: ALS-AWN-0012 | B1584: Outdoor Living & Shading | C1584: Awnings & Canopy Shading | D1584: Retractable Fabric Awning, Aluminium Cassette — 5000x3000mm — Charcoal Grey (RAL 7016) | E1584: Retractable Fabric Awning, Aluminium Cassette | F1584: 5000x3000mm | G1584: Charcoal Grey (RAL 7016) | H1584: N/A | I1584: Each | J1584: Residential/Commercial | K1584: Made-to-Order | L1584: LIGHT | M1584: 5000 | N1584: 3000 | P1584: =(M1584*N1584/1000000)*INDEX(AreaRate_Vals,MATCH(C1584,AreaRate_Keys,0))+INDEX(Hardware_Vals,MATCH("Awnings & Canopy Shading",Hardware_Keys,0)) -> 18350 | Q1584: =INDEX(Markup_Vals,MATCH("Outdoor Living & Shading",MarkupCat_Keys,0)) -> 0.45 | R1584: =P1584*(1+Q1584) -> 26607.5 | S1584: =R1584*(1-TradeDiscount) -> 23414.6 | T1584: =R1584*(1-VolumeDiscount) -> 21286
... A1608: ALS-AWN-0036 | B1608: Outdoor Living & Shading | C1608: Awnings & Canopy Shading | D1608: Fixed Aluminium Slat Canopy — 5000x3000mm — Charcoal Grey (RAL 7016) | E1608: Fixed Aluminium Slat Canopy | F1608: 5000x3000mm | G1608: Charcoal Grey (RAL 7016) | H1608: N/A | I1608: Each | J1608: Residential/Commercial | K1608: Made-to-Order | L1608: LIGHT | M1608: 5000 | N1608: 3000 | P1608: =(M1608*N1608/1000000)*INDEX(AreaRate_Vals,MATCH(C1608,AreaRate_Keys,0))+INDEX(Hardware_Vals,MATCH("Awnings & Canopy Shading",Hardware_Keys,0)) -> 18350 | Q1608: =INDEX(Markup_Vals,MATCH("Outdoor Living & Shading",MarkupCat_Keys,0)) -> 0.45 | R1608: =P1608*(1+Q1608) -> 26607.5 | S1608: =R1608*(1-TradeDiscount) -> 23414.6 | T1608: =R1608*(1-VolumeDiscount) -> 21286
A1609: ALS-BAL-0001 | B1609: Railing & Screening Systems | C1609: Balustrades & Railings | D1609: Aluminium Glass-Infill Balustrade (Post & Handrail) — 1.0m run — Natural Anodised | E1609: Glass-Infill Balustrade (Post & Handrail) | F1609: 1.0m run | G1609: Natural Anodised | H1609: 10mm Toughened Glass | I1609: Per Run | J1609: Residential/Commercial/Institutional | K1609: Made-to-Order | L1609: BALUSTRADE | O1609: 1 | P1609: =(O1609*(INDEX(FrameWeight_Vals,MATCH(L1609,FrameWeight_Keys,0))*AlumCostPerKg+INDEX(Finish_Vals,MATCH(G1609,Finish_Keys,0)))+O1609*INDEX(InfillRun_Vals,MATCH(E1609,InfillRun_Keys,0))) -> 2250.9 | Q1609: =INDEX(Markup_Vals,MATCH("Railing & Screening Systems",MarkupCat_Keys,0)) -> 0.42 | R1609: =P1609*(1+Q1609) -> 3196.278 | S1609: =R1609*(1-TradeDiscount) -> 2812.7246 | T1609: =R1609*(1-VolumeDiscount) -> 2557.0224
A1610: ALS-BAL-0002 | B1610: Railing & Screening Systems | C1610: Balustrades & Railings | D1610: Aluminium Glass-Infill Balustrade (Post & Handrail) — 1.0m run — Satin White (RAL 9016) | E1610: Glass-Infill Balustrade (Post & Handrail) | F1610: 1.0m run | G1610: Satin White (RAL 9016) | H1610: 10mm Toughened Glass | I1610: Per Run | J1610: Residential/Commercial/Institutional | K1610: Made-to-Order | L1610: BALUSTRADE | O1610: 1 | P1610: =(O1610*(INDEX(FrameWeight_Vals,MATCH(L1610,FrameWeight_Keys,0))*AlumCostPerKg+INDEX(Finish_Vals,MATCH(G1610,Finish_Keys,0)))+O1610*INDEX(InfillRun_Vals,MATCH(E1610,InfillRun_Keys,0))) -> 2263.9 | Q1610: =INDEX(Markup_Vals,MATCH("Railing & Screening Systems",MarkupCat_Keys,0)) -> 0.42 | R1610: =P1610*(1+Q1610) -> 3214.738 | S1610: =R1610*(1-TradeDiscount) -> 2828.9694 | T1610: =R1610*(1-VolumeDiscount) -> 2571.7904
A1611: ALS-BAL-0003 | B1611: Railing & Screening Systems | C1611: Balustrades & Railings | D1611: Aluminium Glass-Infill Balustrade (Post & Handrail) — 1.0m run — Charcoal Grey (RAL 7016) | E1611: Glass-Infill Balustrade (Post & Handrail) | F1611: 1.0m run | G1611: Charcoal Grey (RAL 7016) | H1611: 10mm Toughened Glass | I1611: Per Run | J1611: Residential/Commercial/Institutional | K1611: Made-to-Order | L1611: BALUSTRADE | O1611: 1 | P1611: =(O1611*(INDEX(FrameWeight_Vals,MATCH(L1611,FrameWeight_Keys,0))*AlumCostPerKg+INDEX(Finish_Vals,MATCH(G1611,Finish_Keys,0)))+O1611*INDEX(InfillRun_Vals,MATCH(E1611,InfillRun_Keys,0))) -> 2263.9 | Q1611: =INDEX(Markup_Vals,MATCH("Railing & Screening Systems",MarkupCat_Keys,0)) -> 0.42 | R1611: =P1611*(1+Q1611) -> 3214.738 | S1611: =R1611*(1-TradeDiscount) -> 2828.9694 | T1611: =R1611*(1-VolumeDiscount) -> 2571.7904
A1612: ALS-BAL-0004 | B1612: Railing & Screening Systems | C1612: Balustrades & Railings | D1612: Aluminium Glass-Infill Balustrade (Post & Handrail) — 1.0m run — Bronze Anodised | E1612: Glass-Infill Balustrade (Post & Handrail) | F1612: 1.0m run | G1612: Bronze Anodised | H1612: 10mm Toughened Glass | I1612: Per Run | J1612: Residential/Commercial/Institutional | K1612: Made-to-Order | L1612: BALUSTRADE | O1612: 1 | P1612: =(O1612*(INDEX(FrameWeight_Vals,MATCH(L1612,FrameWeight_Keys,0))*AlumCostPerKg+INDEX(Finish_Vals,MATCH(G1612,Finish_Keys,0)))+O1612*INDEX(InfillRun_Vals,MATCH(E1612,InfillRun_Keys,0))) -> 2280.9 | Q1612: =INDEX(Markup_Vals,MATCH("Railing & Screening Systems",MarkupCat_Keys,0)) -> 0.42 | R1612: =P1612*(1+Q1612) -> 3238.878 | S1612: =R1612*(1-TradeDiscount) -> 2850.2126 | T1612: =R1612*(1-VolumeDiscount) -> 2591.1024
A1613: ALS-BAL-0005 | B1613: Railing & Screening Systems | C1613: Balustrades & Railings | D1613: Aluminium Glass-Infill Balustrade (Post & Handrail) — 2.0m run — Natural Anodised | E1613: Glass-Infill Balustrade (Post & Handrail) | F1613: 2.0m run | G1613: Natural Anodised | H1613: 10mm Toughened Glass | I1613: Per Run | J1613: Residential/Commercial/Institutional | K1613: Made-to-Order | L1613: BALUSTRADE | O1613: 2 | P1613: =(O1613*(INDEX(FrameWeight_Vals,MATCH(L1613,FrameWeight_Keys,0))*AlumCostPerKg+INDEX(Finish_Vals,MATCH(G1613,Finish_Keys,0)))+O1613*INDEX(InfillRun_Vals,MATCH(E1613,InfillRun_Keys,0))) -> 4501.8 | Q1613: =INDEX(Markup_Vals,MATCH("Railing & Screening Systems",MarkupCat_Keys,0)) -> 0.42 | R1613: =P1613*(1+Q1613) -> 6392.556 | S1613: =R1613*(1-TradeDiscount) -> 5625.4493 | T1613: =R1613*(1-VolumeDiscount) -> 5114.0448
A1614: ALS-BAL-0006 | B1614: Railing & Screening Systems | C1614: Balustrades & Railings | D1614: Aluminium Glass-Infill Balustrade (Post & Handrail) — 2.0m run — Satin White (RAL 9016) | E1614: Glass-Infill Balustrade (Post & Handrail) | F1614: 2.0m run | G1614: Satin White (RAL 9016) | H1614: 10mm Toughened Glass | I1614: Per Run | J1614: Residential/Commercial/Institutional | K1614: Made-to-Order | L1614: BALUSTRADE | O1614: 2 | P1614: =(O1614*(INDEX(FrameWeight_Vals,MATCH(L1614,FrameWeight_Keys,0))*AlumCostPerKg+INDEX(Finish_Vals,MATCH(G1614,Finish_Keys,0)))+O1614*INDEX(InfillRun_Vals,MATCH(E1614,InfillRun_Keys,0))) -> 4527.8 | Q1614: =INDEX(Markup_Vals,MATCH("Railing & Screening Systems",MarkupCat_Keys,0)) -> 0.42 | R1614: =P1614*(1+Q1614) -> 6429.476 | S1614: =R1614*(1-TradeDiscount) -> 5657.9389 | T1614: =R1614*(1-VolumeDiscount) -> 5143.5808
A1615: ALS-BAL-0007 | B1615: Railing & Screening Systems | C1615: Balustrades & Railings | D1615: Aluminium Glass-Infill Balustrade (Post & Handrail) — 2.0m run — Charcoal Grey (RAL 7016) | E1615: Glass-Infill Balustrade (Post & Handrail) | F1615: 2.0m run | G1615: Charcoal Grey (RAL 7016) | H1615: 10mm Toughened Glass | I1615: Per Run | J1615: Residential/Commercial/Institutional | K1615: Made-to-Order | L1615: BALUSTRADE | O1615: 2 | P1615: =(O1615*(INDEX(FrameWeight_Vals,MATCH(L1615,FrameWeight_Keys,0))*AlumCostPerKg+INDEX(Finish_Vals,MATCH(G1615,Finish_Keys,0)))+O1615*INDEX(InfillRun_Vals,MATCH(E1615,InfillRun_Keys,0))) -> 4527.8 | Q1615: =INDEX(Markup_Vals,MATCH("Railing & Screening Systems",MarkupCat_Keys,0)) -> 0.42 | R1615: =P1615*(1+Q1615) -> 6429.476 | S1615: =R1615*(1-TradeDiscount) -> 5657.9389 | T1615: =R1615*(1-VolumeDiscount) -> 5143.5808
A1616: ALS-BAL-0008 | B1616: Railing & Screening Systems | C1616: Balustrades & Railings | D1616: Aluminium Glass-Infill Balustrade (Post & Handrail) — 2.0m run — Bronze Anodised | E1616: Glass-Infill Balustrade (Post & Handrail) | F1616: 2.0m run | G1616: Bronze Anodised | H1616: 10mm Toughened Glass | I1616: Per Run | J1616: Residential/Commercial/Institutional | K1616: Made-to-Order | L1616: BALUSTRADE | O1616: 2 | P1616: =(O1616*(INDEX(FrameWeight_Vals,MATCH(L1616,FrameWeight_Keys,0))*AlumCostPerKg+INDEX(Finish_Vals,MATCH(G1616,Finish_Keys,0)))+O1616*INDEX(InfillRun_Vals,MATCH(E1616,InfillRun_Keys,0))) -> 4561.8 | Q1616: =INDEX(Markup_Vals,MATCH("Railing & Screening Systems",MarkupCat_Keys,0)) -> 0.42 | R1616: =P1616*(1+Q1616) -> 6477.756 | S1616: =R1616*(1-TradeDiscount) -> 5700.4253 | T1616: =R1616*(1-VolumeDiscount) -> 5182.2048
...
